Workbook

Sheet Empreendimentos
A1: DIVISÃO DE AREAS PARA TORRES
A2: Master Plan - Rev06
A3: Data: 03/11/25
A5: ITEM | B5: QUADRAS / LOTE | E5: COEFICIENTE URBANISTICO | H5: ÁREAS | J5: TERRENO | L5: EDIFICIOS
B6: n° | C6: uso | D6: área | E6: coef. restrição | F6: % aprov. | G6: coef. considerado | H6: privativa | I6: construída | J6: unid. | K6: área média | L6: unid. | M6: área média apto. | N6: apto. / andar | O6: nº de pav.
A8: AL'DORA TOWN - VERSAILLES | D8: =SUM(D9,D32,D34) -> 42784.62 | H8: =SUM(H9,H32,H34) -> 125684.4 | I8: =SUM(I9,I32,I34) -> 206039.99 | L8: =SUM(L9,L32,L34) -> 14 | Q8: =L8+L57+L76+L104+L130+L126 -> 135 | R8: =Q8*150*2.8 -> 56700
A9: 1.0 | B9: QC01 | C9: Resid. Multifamiliar | D9: =SUM(D10:D30) -> 20598.71 | H9: =SUM(H10:H30) -> 49908.032 | I9: =SUM(I10:I30) -> 81816.446 | L9: =SUM(L10:L30) -> 6 | M9: =H9/N9 -> 75.848073 | N9: =SUMPRODUCT(N10:N30,O10:O30) -> 658
B10: LT01 | C10: Resid. Multifamiliar | D10: 1802.63 | E10: 4 | F10: 0.8 | G10: =E10*F10 -> 3.2 | H10: =D10*G10 -> 5768.416 | I10: =H10/0.61 -> 9456.4197 | J10: 1 | K10: =D10/J10 -> 1802.63 | L10: =J10 -> 1 | M10: =H10/(N10*O10) -> 56.553098 | N10: 6 | O10: 17
B11: LT02 | C11: Resid. Multifamiliar | D11: 2413.25 | E11: 4 | F11: 0.8 | G11: =E11*F11 -> 3.2 | H11: =D11*G11 -> 7722.4 | I11: =H11/0.61 -> 12659.672 | J11: 1 | K11: =D11/J11 -> 2413.25 | L11: =J11 -> 1 | M11: =H11/(N11*O11) -> 64.353333 | N11: 6 | O11: 20
B12: LT03 | C12: Lote misto - Venda | D12: 360 | J12: 1 | K12: =D12/J12 -> 360
B13: LT04 | C13: Lote misto - Venda | D13: 360 | J13: 1 | K13: =D13/J13 -> 360
B14: LT05 | C14: Lote misto - Venda | D14: 360 | J14: 1 | K14: =D14/J14 -> 360
B15: LT06 | C15: Lote misto - Venda | D15: 360 | J15: 1 | K15: =D15/J15 -> 360
B16: LT07 | C16: Lote misto - Venda | D16: 360 | J16: 1 | K16: =D16/J16 -> 360
B17: LT08 | C17: Lote misto - Venda | D17: 360 | J17: 1 | K17: =D17/J17 -> 360
B18: LT09 | C18: Lote misto - Venda | D18: 360 | J18: 1 | K18: =D18/J18 -> 360
B19: LT10 | C19: Resid. Multifamiliar | D19: 2423.05 | E19: 4 | F19: 0.8 | G19: =E19*F19 -> 3.2 | H19: =D19*G19 -> 7753.76 | I19: =H19/0.61 -> 12711.082 | J19: 1 | K19: =D19/J19 -> 2423.05 | L19: =J19 -> 1 | M19: =H19/(N19*O19) -> 64.614667 | N19: 6 | O19: 20
B20: LT11 | C20: Resid. Multifamiliar | D20: 2652.8 | E20: 4 | F20: 0.8 | G20: =E20*F20 -> 3.2 | H20: =D20*G20 -> 8488.96 | I20: =H20/0.61 -> 13916.328 | J20: 1 | K20: =D20/J20 -> 2652.8 | L20: =J20 -> 1 | M20: =H20/(N20*O20) -> 70.741333 | N20: 6 | O20: 20
B21: LT12 | C21: Lote misto - Venda | D21: 360 | J21: 1 | K21: =D21/J21 -> 360
B22: LT13 | C22: Lote misto - Venda | D22: 360 | J22: 1 | K22: =D22/J22 -> 360
B23: LT14 | C23: Lote misto - Venda | D23: 360 | J23: 1 | K23: =D23/J23 -> 360
B24: LT15 | C24: Lote misto - Venda | D24: 360 | J24: 1 | K24: =D24/J24 -> 360
B25: LT16 | C25: Lote misto - Venda | D25: 360 | J25: 1 | K25: =D25/J25 -> 360
B26: LT17 | C26: Lote misto - Venda | D26: 360 | J26: 1 | K26: =D26/J26 -> 360
B27: LT18 | C27: Lote misto - Venda | D27: 360 | J27: 1 | K27: =D27/J27 -> 360
B28: LT19 | C28: Lote misto - Venda | D28: 360 | J28: 1 | K28: =D28/J28 -> 360
B29: LT20 | C29: Resid. Multifamiliar | D29: 2726.58 | E29: 4 | F29: 0.8 | G29: =E29*F29 -> 3.2 | H29: =D29*G29 -> 8725.056 | I29: =H29/0.61 -> 14303.37 | J29: 1 | K29: =D29/J29 -> 2726.58 | L29: =J29 -> 1 | M29: =H29/(N29*O29) -> 87.25056 | N29: 5 | O29: 20
B30: LT21 | C30: Resid. Multifamiliar com fachada ativa | D30: 3180.4 | E30: 4 | F30: 0.9 | G30: =E30*F30 -> 3.6 | H30: =D30*G30 -> 11449.44 | I30: =H30/0.61 -> 18769.574 | J30: 1 | K30: =D30/J30 -> 3180.4 | L30: =J30 -> 1 | M30: =H30/(N30*O30) -> 119.265 | N30: 4 | O30: 24
A32: 2.0 | B32: QC02 | C32: Resid. Multifamiliar com fachada ativa | D32: 11953.63 | E32: 4 | F32: 0.9 | G32: =E32*F32 -> 3.6 | H32: =D32*G32 -> 43033.068 | I32: =H32/0.61 -> 70546.013 | J32: 4 | K32: =D32/J32 -> 2988.4075 | L32: =J32 -> 4 | M32: =(H32/L32)/(N32*O32) -> 112.06528 | N32: 4 | O32: 24
A34: 3.0 | B34: QC03 | C34: Resid. Multifamiliar com fachada ativa | D34: =10232.28 -> 10232.28 | E34: 4 | F34: 0.8 | G34: =E34*F34 -> 3.2 | H34: =D34*G34 -> 32743.296 | I34: =H34/0.61 -> 53677.534 | J34: 4 | K34: =D34/J34 -> 2558.07 | L34: =J34 -> 4 | M34: =(H34/L34)/(N34*O34) -> 102.3228 | N34: 4 | O34: 20
A36: 4.0 | B36: AI | C36: Park | D36: =(602-30)*30 -> 17160 | F36: =(D36/(20598.71+D32+D34)) -> 0.40107871
C37: Núcleo recreativos e cultural | D37: =100*3+3000 -> 3300 | F37: =(D37/(20598.71+D32+D34)) -> 0.07713052
C38: Paisagismos e caminhos verdes e culturais | D38: =D36-D37 -> 13860
A41: JARDIM CHAMBORD
A42: 1.0 | B42: JC | D42: =SUM(D43:D54) -> 128940.25 | H42: =SUM(H43:H54) -> 128940.25 | I42: =SUM(I43:I54) -> 0 | J42: =SUM(J43:J54) -> 208 | K42: =H42/J42 -> 619.90505
B43: Q01 | C43: Residencial unifamiliar | D43: 3016.52 | H43: =D43 -> 3016.52 | J43: 5 | K43: =D43/J43 -> 603.304 | Q43: =55*6 -> 330
B44: Q02 | C44: Residencial unifamiliar | D44: 13591.31 | H44: =D44 -> 13591.31 | J44: 22 | K44: =D44/J44 -> 617.78682
B45: Q03 | C45: Residencial unifamiliar | D45: 11309.04 | H45: =D45 -> 11309.04 | J45: 18 | K45: =D45/J45 -> 628.28
B46: Q04 | C46: Residencial unifamiliar | D46: 13413.04 | H46: =D46 -> 13413.04 | J46: 20 | K46: =D46/J46 -> 670.652
B47: Q05 | C47: Residencial unifamiliar | D47: 9773.57 | H47: =D47 -> 9773.57 | J47: 17 | K47: =D47/J47 -> 574.91588
B48: Q06 | C48: Residencial unifamiliar | D48: 4375.69 | H48: =D48 -> 4375.69 | J48: 7 | K48: =D48/J48 -> 625.09857
B49: Q07 | C49: Residencial unifamiliar | D49: 8179.16 | H49: =D49 -> 8179.16 | J49: 12 | K49: =D49/J49 -> 681.59667
B50: Q08 | C50: Residencial unifamiliar | D50: 13461.88 | H50: =D50 -> 13461.88 | J50: 23 | K50: =D50/J50 -> 585.29913
B51: Q09 | C51: Residencial unifamiliar | D51: 19718.74 | H51: =D51 -> 19718.74 | J51: 35 | K51: =D51/J51 -> 563.39257
B52: Q10 | C52: Residencial unifamiliar | D52: 10936.27 | H52: =D52 -> 10936.27 | J52: 17 | K52: =D52/J52 -> 643.31
B53: Q11 | C53: Residencial unifamiliar | D53: 16339.54 | H53: =D53 -> 16339.54 | J53: 25 | K53: =D53/J53 -> 653.5816
B54: Q12 | C54: Residencial unifamiliar | D54: 4825.49 | H54: =D54 -> 4825.49 | J54: 7 | K54: =D54/J54 -> 689.35571
A57: AL'DORA TOWN | L57: =SUM(L58,L67,L69) -> 13
A58: 1.0 | B58: QAT01 | C58: Residencial multifamiliar | D58: 12062.738 | E58: 4 | F58: 0.9 | G58: =E58*F58 -> 3.6 | H58: =D58*G58 -> 43425.856 | I58: =H58/0.61 -> 71189.927 | J58: 4 | K58: =D58/J58 -> 3015.6844 | L58: =J58 -> 4 | M58: =(H58/L58)/(N58*O58) -> 104.38908 | N58: 4 | O58: 26
A60: 2.0 | B60: QAT02 | C60: Mall | D60: 8925.08 | E60: 4 | F60: 0.2 | G60: =E60*F60 -> 0.8 | H60: =D60*G60 -> 7140.064 | I60: =H60/0.8 -> 8925.08 | J60: 1 | K60: =D60/J60 -> 8925.08 | L60: =J60 -> 1 | M60: =(H60/L60)/(N60*O60) -> 2380.0213 | N60: 1 | O60: 3 | Q60: Ref. Pátio Vinhedos
A62: 3.0 | B62: QAT03 | D62: 15349.12 | E62: 4 | F62: 0.9 | G62: =E62*F62 -> 3.6 | H62: =D62*G62 -> 55256.832 | I62: =E62*H62 -> 221027.33 | J62: 4 | K62: =D62/J62 -> 3837.28 | L62: =J62 -> 4 | M62: =(H62/L62)/(N62*O62) -> 164.45486 | N62: 4 | O62: 21
C63: Escola Infantil | D63: 3514.04 | E63: 4 | F63: =1909.47/3514.04/4 -> 0.13584578 | G63: =E63*F63 -> 0.54338311 | H63: =D63*G63 -> 1909.47 | I63: =H63 -> 1909.47 | L63: 1 | Q63: Ref. Gabarito
C64: Escola Fundamental | D64: 3607.11 | E64: 4 | F64: =1710.59/3607.11/4 -> 0.11855682 | G64: =E64*F64 -> 0.47422729 | H64: =D64*G64 -> 1710.59 | I64: =H64 -> 1710.59 | L64: 1 | Q64: Ref. FNDE
C65: Corporativo | D65: =D62-D63-D64 -> 8227.97 | E65: 4 | F65: 0.55 | G65: =E65*F65 -> 2.2 | H65: =D65*G65 -> 18101.534 | I65: =H65/0.61 -> 29674.646 | J65: 2 | K65: =D65/J65 -> 4113.985 | L65: =J65 -> 2 | M65: =H65/(N65*O65) -> 952.71232 | N65: 1 | O65: 19 | Q65: Ref. Torre sul
A67: 4.0 | B67: QAT04 | C67: Residencial | D67: 11944.37 | E67: 4 | F67: 0.9 | G67: =E67*F67 -> 3.6 | H67: =D67*G67 -> 42999.732 | I67: =H67/0.61 -> 70491.364 | J67: 4 | K67: =D67/J67 -> 2986.0925 | L67: =J67 -> 4 | M67: =(H67/L67)/(N67*O67) -> 223.95694 | N67: 2 | O67: 24
A69: 4.0 | B69: QAT05 | C69: Residencial | D69: 16481.909 | E69: 4 | F69: 0.9 | G69: =E69*F69 -> 3.6 | H69: =D69*G69 -> 59334.873 | I69: =H69/0.61 -> 97270.284 | J69: 5 | K69: =D69/J69 -> 3296.3818 | L69: =J69 -> 5 | M69: =(H69/L69)/(N69*O69) -> 164.81909 | N69: 3 | O69: 24
A72: JARDIM 03
A73: 1.0 | B73: J03 | D73: 156094.41 | H73: =D73*0.55 -> 85851.927 | J73: 180 | K73: =H73/J73 -> 476.95515
A76: AL'DORA PARK | L76: =SUM(L77,L79,L85,L87,L89,L91,L93,L95,L97) -> 48
A77: 1.0 | B77: QAP01 | C77: Residencial | D77: 19082.03 | E77: 4 | F77: 0.8 | G77: =E77*F77 -> 3.2 | H77: =D77*G77 -> 61062.496 | I77: =H77/0.61 -> 100102.45 | J77: 8 | K77: =D77/J77 -> 2385.2537 | L77: =J77 -> 8 | M77: =(H77/L77)/(N77*O77) -> 63.606767 | N77: 6 | O77: 20
A79: 2.0 | B79: QAP02 | C79: Residencial | D79: 18711.19 | E79: 3.5 | F79: 0.85 | G79: =E79*F79 -> 2.975 | H79: =D79*G79 -> 55665.789 | I79: =H79/0.61 -> 91255.392 | J79: 7 | K79: =D79/J79 -> 2673.0271 | L79: =J79 -> 7 | M79: =(H79/L79)/(N79*O79) -> 66.268796 | N79: 6 | O79: 20 | Q79: Ref. Pátio Vinhedos
A81: 3.0 | B81: QAP03 | C81: Área publica | D81: 8934.8409
A83: 4.0 | B83: QAP04 | C83: Mall | D83: 12409.301 | E83: 4 | F83: 0.2 | G83: =E83*F83 -> 0.8 | H83: =D83*G83 -> 9927.441 | I83: =H83/0.61 -> 16274.493 | J83: 1 | K83: =D83/J83 -> 12409.301 | L83: =J83 -> 1 | M83: =(H83/L83)/(N83*O83) -> 3309.147 | N83: 1 | O83: 3
A85: 5.0 | B85: QAP05 | C85: Residencial | D85: 11314.618 | E85: 4 | F85: 0.9 | G85: =E85*F85 -> 3.6 | H85: =D85*G85 -> 40732.625 | I85: =H85/0.61 -> 66774.795 | J85: 4 | K85: =D85/J85 -> 2828.6545 | L85: =J85 -> 4 | M85: =(H85/L85)/(N85*O85) -> 115.71768 | N85: 4 | O85: 22
A87: 6.0 | B87: QAP06 | C87: Residencial | D87: 7360.2675 | E87: 4 | F87: 0.9 | G87: =E87*F87 -> 3.6 | H87: =D87*G87 -> 26496.963 | I87: =H87/0.61 -> 43437.644 | J87: 3 | K87: =D87/J87 -> 2453.4225 | L87: =J87 -> 3 | M87: =(H87/L87)/(N87*O87) -> 100.36728 | N87: 4 | O87: 22
A89: 7.0 | B89: QAP07 | C89: Residencial | D89: 9167.2477 | E89: 4 | F89: 0.9 | G89: =E89*F89 -> 3.6 | H89: =D89*G89 -> 33002.092 | I89: =H89/0.61 -> 54101.79 | J89: 4 | K89: =D89/J89 -> 2291.8119 | L89: =J89 -> 4 | M89: =(H89/L89)/(N89*O89) -> 93.755942 | N89: 4 | O89: 22
A91: 8.0 | B91: QAP08 | C91: Residencial | D91: 18869.75 | E91: =(3.5+3)/2 -> 3.25 | F91: 0.9 | G91: =E91*F91 -> 2.925 | H91: =D91*G91 -> 55194.018 | I91: =H91/0.61 -> 90481.997 | J91: 6 | K91: =D91/J91 -> 3144.9583 | L91: =J91 -> 6 | M91: =(H91/L91)/(N91*O91) -> 104.53413 | N91: 4 | O91: 22
A93: 9.0 | B93: QAP09 | C93: Residencial | D93: 13413.368 | E93: 3 | F93: 0.9 | G93: =E93*F93 -> 2.7 | H93: =D93*G93 -> 36216.093 | I93: =H93/0.61 -> 59370.643 | J93: 4 | K93: =D93/J93 -> 3353.3419 | L93: =J93 -> 4 | M93: =(H93/L93)/(N93*O93) -> 102.88663 | N93: 4 | O93: 22
A95: 10.0 | B95: QAP10 | C95: Residencial | D95: 24010.537 | E95: =(3.5+3)/2 -> 3.25 | F95: 0.9 | G95: =E95*F95 -> 2.925 | H95: =D95*G95 -> 70230.82 | I95: =H95/0.61 -> 115132.49 | J95: 7 | K95: =D95/J95 -> 3430.0767 | L95: =J95 -> 7 | M95: =(H95/L95)/(N95*O95) -> 114.01107 | N95: 4 | O95: 22
A97: 11.0 | B97: QAP11 | C97: Residencial | D97: 13352.134 | E97: 3 | F97: 0.9 | G97: =E97*F97 -> 2.7 | H97: =D97*G97 -> 36050.761 | I97: =H97/0.61 -> 59099.609 | J97: 5 | K97: =D97/J97 -> 2670.4268 | L97: =J97 -> 5 | M97: =(H97/L97)/(N97*O97) -> 81.933548 | N97: 4 | O97: 22
A99: 12.0 | B99: QAP12 | C99: Área publica | D99: 4195.1555
A101: 13.0 | B101: QAPark | C101: Área publica | D101: 30160.271
A104: AL'DORA VITTA | L104: =SUM(L109,L111,L113,L115,L117,L119,L121) -> 31
A105: 1.0 | B105: QAV01 | C105: Mall | D105: 7899.0765 | E105: 4 | F105: 0.2 | G105: =E105*F105 -> 0.8 | H105: =D105*G105 -> 6319.2612 | I105: =H105/0.8 -> 7899.0765 | J105: 1 | K105: =D105/J105 -> 7899.0765 | L105: =J105 -> 1 | M105: =(H105/L105)/(N105*O105) -> 2106.4204 | N105: 1 | O105: 3
A107: 2.0 | B107: QAV02 | C107: Área publica | D107: 4919.1 | Q107: Ref. Pátio Vinhedos
A109: 2.0 | B109: QAV03 | C109: Residencial | D109: 18230.486 | E109: =(3.5+3)/2 -> 3.25 | F109: 0.9 | G109: =E109*F109 -> 2.925 | H109: =D109*G109 -> 53324.172 | I109: =H109/0.61 -> 87416.675 | J109: 4 | K109: =D109/J109 -> 4557.6215 | L109: =J109 -> 4 | M109: =(H109/L109)/(N109*O109) -> 138.86503 | N109: 4 | O109: 24 | Q109: Ref. Pátio Vinhedos
A111: 4.0 | B111: QAV04 | C111: Residencial | D111: 11688.197 | E111: 3.5 | F111: 0.9 | G111: =E111*F111 -> 3.15 | H111: =D111*G111 -> 36817.819 | I111: =H111/0.61 -> 60357.08 | J111: 4 | K111: =D111/J111 -> 2922.0491 | L111: =J111 -> 4 | M111: =(H111/L111)/(N111*O111) -> 95.879737 | N111: 4 | O111: 24
A113: 5.0 | B113: QAV05 | C113: Residencial | D113: 15361.844 | E113: 3.5 | F113: 0.9 | G113: =E113*F113 -> 3.15 | H113: =D113*G113 -> 48389.809 | I113: =H113/0.61 -> 79327.555 | J113: 5 | K113: =D113/J113 -> 3072.3688 | L113: =J113 -> 5 | M113: =(H113/L113)/(N113*O113) -> 100.8121 | N113: 4 | O113: 24
A115: 6.0 | B115: QAV06 | C115: Residencial | D115: 12113.943 | E115: 4 | F115: 0.9 | G115: =E115*F115 -> 3.6 | H115: =D115*G115 -> 43610.196 | I115: =H115/0.61 -> 71492.124 | J115: 4 | K115: =D115/J115 -> 3028.4858 | L115: =J115 -> 4 | M115: =(H115/L115)/(N115*O115) -> 113.56822 | N115: 4 | O115: 24
A117: 7.0 | B117: QAV07 | C117: Residencial | D117: 21476.594 | E117: 3.5 | F117: 0.9 | G117: =E117*F117 -> 3.15 | H117: =D117*G117 -> 67651.27 | I117: =H117/0.61 -> 110903.72 | J117: 5 | K117: =D117/J117 -> 4295.3187 | L117: =J117 -> 5 | M117: =(H117/L117)/(N117*O117) -> 140.94015 | N117: 4 | O117: 24
A119: 8.0 | B119: QAV08 | C119: Residencial | D119: 11867.325 | E119: 3.5 | F119: 0.8 | G119: =E119*F119 -> 2.8 | H119: =D119*G119 -> 33228.51 | I119: =H119/0.61 -> 54472.968 | J119: 4 | K119: =D119/J119 -> 2966.8313 | L119: =J119 -> 4 | M119: =(H119/L119)/(N119*O119) -> 57.688386 | N119: 6 | O119: 24
A121: 9.0 | B121: QAV09 | C121: Residencial | D121: 13664.937 | E121: 4 | F121: 0.8 | G121: =E121*F121 -> 3.2 | H121: =D121*G121 -> 43727.8 | I121: =H121/0.61 -> 71684.918 | J121: 5 | K121: =D121/J121 -> 2732.9875 | L121: =J121 -> 5 | M121: =(H121/L121)/(N121*O121) -> 60.733055 | N121: 6 | O121: 24
A124: AL'DORA NEXUS GENOVA
A125: 1.0 | B125: J03 | D125: 156094.41 | H125: =D125 -> 156094.41 | J125: 180 | K125: =H125/J125 -> 867.19118
C126: Comercial / Corporativos | D126: =26917.34-D127 -> 24494.779 | E126: 3.5 | F126: 0.42 | G126: =E126*F126 -> 1.47 | H126: =D126*G126 -> 36007.326 | I126: =H126/0.5 -> 72014.651 | J126: 5 | K126: =D126/J126 -> 4898.9559 | L126: =J126 -> 5 | M126: =H126/(N126*O126) -> 1800.3663 | N126: 5 | O126: 4 | Q126: Ref. Aruã
C127: Área publica | D127: =26917.34*9% -> 2422.5606 | H127: =D127*G127 -> 0 | I127: =H127 -> 0
A130: AL'DORA NEXUS | L130: =SUM(L131,L133,L137,L139,L143,L145,L147,L149) -> 24
A131: 1.0 | B131: QAN01 | C131: Corporativo | D131: 15156.883 | E131: 4 | F131: 0.55 | G131: =E131*F131 -> 2.2 | H131: =D131*G131 -> 33345.143 | I131: =H131/0.61 -> 54664.169 | J131: 2 | K131: =D131/J131 -> 7578.4416 | L131: =J131 -> 2 | M131: =H131/(N131*O131) -> 1755.0075 | N131: 1 | O131: 19
A133: 2.0 | B133: QAV02 | C133: Convenções | D133: 10035.69 | E133: 3.5 | F133: 0.2 | G133: =E133*F133 -> 0.7 | H133: =D133*G133 -> 7024.983 | I133: =H133/0.8 -> 8781.2288 | J133: 1 | K133: =D133/J133 -> 10035.69 | L133: =J133 -> 1 | M133: =(H133/L133)/(N133*O133) -> 2341.661 | N133: 1 | O133: 3 | Q133: Ref. Pátio Vinhedos
A135: 2.0 | B135: QAV03 | C135: Área publica | D135: 5435.83 | Q135: Ref. Pátio Vinhedos
A137: 4.0 | B137: QAV04 | C137: Resid. / Corporativo / fachada ativa | D137: 25846.67 | E137: 4 | F137: 0.8 | G137: =E137*F137 -> 3.2 | H137: =D137*G137 -> 82709.344 | I137: =H137/0.61 -> 135589.09 | J137: 8 | K137: =D137/J137 -> 3230.8337 | L137: =J137 -> 8 | O137: 22
A139: 5.0 | B139: QAV05 | C139: Resid. / Corporativo / fachada ativa | D139: 12862.887 | E139: 4 | F139: 0.8 | G139: =E139*F139 -> 3.2 | H139: =D139*G139 -> 41161.238 | I139: =H139/0.61 -> 67477.439 | J139: 4 | K139: =D139/J139 -> 3215.7217 | L139: =J139 -> 4 | O139: 24
A141: 6.0 | B141: QAV06 | C141: Área publica | D141: 4559.0002
A143: 7.0 | B143: QAV07 | C143: Resid. / Corporativo / fachada ativa | D143: 9879.2721 | E143: 4 | F143: 0.8 | G143: =E143*F143 -> 3.2 | H143: =D143*G143 -> 31613.671 | I143: =H143/0.61 -> 51825.69 | J143: 3 | K143: =D143/J143 -> 3293.0907 | L143: =J143 -> 3 | O143: 24
A145: 8.0 | B145: QAV08 | C145: Corporativo | D145: 7399.5601 | E145: 4 | F145: 0.55 | G145: =E145*F145 -> 2.2 | H145: =D145*G145 -> 16279.032 | I145: =H145/0.61 -> 26686.938 | J145: 2 | K145: =D145/J145 -> 3699.78 | L145: =J145 -> 2 | O145: 20
A147: 9.0 | B147: QAV09 | C147: Corporativo | D147: 5555.8973 | E147: 3.5 | F147: 0.42 | G147: =E147*F147 -> 1.47 | H147: =D147*G147 -> 8167.169 | I147: =H147/0.5 -> 16334.338 | J147: 2 | K147: =D147/J147 -> 2777.9486 | L147: =J147 -> 2 | O147: 4
C149: Corporativo | D149: 5555.8973 | E149: 3.5 | F149: 0.42 | G149: =E149*F149 -> 1.47 | H149: =D149*G149 -> 8167.169 | I149: =H149/0.5 -> 16334.338 | J149: 2 | K149: =D149/J149 -> 2777.9486 | L149: =J149 -> 2 | O149: 4
A152: JARDIM 04
A153: 1.0 | B153: J04 | D153: 238616.86 | H153: =D153*0.55 -> 131239.27 | J153: 260 | K153: =H153/J153 -> 504.76643
A156: JARDIM 05
...

Sheet Cromograma Fisico Financeiro
A2: CRONOGRAMA FÍSICO-FINANCEIRO
A3: CLIENTE: | B3: CIDADE JARDIM EMPREENDIMENTOS
A4: OBRA: | B4: AL' DORA CIDADE JARDIM
A5: DATA | B5: 45968
A6: REVISÃO: | B6: 01
A8: DISCRIMINAÇÃO | C8: PADRÃO | D8: EDIFICIO | E8: =Empreendimentos!H5 -> ÁREAS | H8: VALORES ( R$ ) | J8: ( % ) | L8: 1° ano | M8: 2° ano | N8: 3° ano | O8: 4° ano | P8: 5° ano | Q8: 6° ano | R8: 7° ano | S8: 8° ano | T8: 9° ano | U8: 10° ano | V8: 11° ano | W8: 12° ano | X8: 13° ano | Y8: 14° ano | Z8: 15° ano | AA8: 16° ano | AB8: 17° ano | AC8: 18° ano | AD8: 19° ano | AE8: 20° ano | AF8: 21° ano | AG8: 22° ano | AH8: 23° ano | AI8: 24° ano | AJ8: 25° ano | AK8: 26° | AL8: 27 | AM8: 28 | AN8: 29 | AO8: 30 | AP8: 31 | AQ8: 32 | AR8: 33 | AS8: 34 | AT8: 35 | AU8: 36 | AV8: 37 | AW8: 38 | AX8: 39 | AY8: 40 | AZ8: 41 | BA8: 42 | BB8: 43 | BC8: 44 | BD8: 45 | BE8: 46 | BF8: 47 | BG8: 48 | BH8: 49 | BI8: 50° ano
E9: unid. | F9: =Empreendimentos!H6 -> privativa | G9: =Empreendimentos!I6 -> construída | H9: VGV | I9: OBRA | J9: =H9 -> VGV | K9: =I9 -> OBRA | L9: 2026 | M9: 2027 | N9: 2028 | O9: 2029 | P9: 2030 | Q9: 2031 | R9: 2032 | S9: 2033 | T9: 2034 | U9: 2035 | V9: 2036 | W9: 2037 | X9: 2038 | Y9: 2039 | Z9: 2040 | AA9: 2041 | AB9: 2042 | AC9: 2043 | AD9: 2044 | AE9: 2045 | AF9: 2046 | AG9: 2047 | AH9: 2048 | AI9: 2049 | AJ9: 2050 | AK9: 2051 | AL9: 2052 | AM9: 2053 | AN9: 2054 | AO9: 2055 | AP9: 2056 | AQ9: 2057 | AR9: 2058 | AS9: 2059 | AT9: 2060 | AU9: 2061 | AV9: 2062 | AW9: 2063 | AX9: 2064 | AY9: 2065 | AZ9: 2066 | BA9: 2067 | BB9: 2068 | BC9: 2069 | BD9: 2070 | BE9: 2071 | BF9: 2072 | BG9: 2073 | BH9: 2074 | BI9: 2075
A11: 1.0 | B11: =Empreendimentos!A8 -> AL'DORA TOWN - VERSAILLES | D11: =Empreendimentos!L8 -> 14 | F11: =Empreendimentos!H8 -> 125684.4 | G11: =Empreendimentos!I8 -> 206039.99 | H11: =SUM(H12,H35,H37,H39) -> 1116394988 | I11: =SUM(I12,I35,I37,I39) -> 6.1583839e+08 | J11: =H11/$H$42 -> 1 | K11: =I11/$I$47 -> 1 | BJ11: =SUM(L11:BI11) -> 0
A12: =Empreendimentos!B9 -> QC01 | B12: =Empreendimentos!C9 -> Resid. Multifamiliar | C12: Standart Plus / Médio | D12: =Empreendimentos!L9 -> 6 | E12: =Empreendimentos!M9 -> 75.848073 | F12: =Empreendimentos!H9 -> 49908.032 | G12: =Empreendimentos!I9 -> 81816.446 | H12: =SUM(H13:H33) -> 4.3440771e+08 | I12: =SUM(I13:I33) -> 2.3969609e+08 | J12: =H12/$H$42 -> 0.3891165 | K12: =I12/$I$47 -> 0.38921915 | BJ12: =SUM(L12:BI12) -> 0
A13: =Empreendimentos!B10 -> LT01 | B13: =Empreendimentos!C10 -> Resid. Multifamiliar | C13: =$C$338 -> Standart Plus | D13: =Empreendimentos!L10 -> 1 | E13: =Empreendimentos!M10 -> 56.553098 | F13: =Empreendimentos!H10 -> 5768.416 | G13: =Empreendimentos!I10 -> 9456.4197 | H13: =F13*VLOOKUP(C13,$C$337:$E$344,2,FALSE) -> 46147328 | I13: =G13*VLOOKUP(C13,$C$337:$E$344,3,FALSE) -> 26556297 | J13: =H13/$H$42 -> 0.041336022 | K13: =I13/$I$47 -> 0.043122185 | L13: 0.02 | M13: 0.03 | N13: 0.04 | O13: 0.06 | P13: 0.07 | Q13: 0.08 | R13: 0.1 | S13: 0.1 | T13: 0.11 | U13: 0.1 | V13: 0.1 | W13: 0.08 | X13: 0.06 | Y13: 0.04 | Z13: 0.01 | BJ13: =SUM(L13:BI13) -> 1
A14: =Empreendimentos!B11 -> LT02 | B14: =Empreendimentos!C11 -> Resid. Multifamiliar | C14: =$C$338 -> Standart Plus | D14: =Empreendimentos!L11 -> 1 | E14: =Empreendimentos!M11 -> 64.353333 | F14: =Empreendimentos!H11 -> 7722.4 | G14: =Empreendimentos!I11 -> 12659.672 | H14: =F14*VLOOKUP(C14,$C$337:$E$344,2,FALSE) -> 61779200 | I14: =G14*VLOOKUP(C14,$C$337:$E$344,3,FALSE) -> 35551934 | J14: =H14/$H$42 -> 0.05533812 | K14: =I14/$I$47 -> 0.057729325 | L14: 0.02 | M14: 0.03 | N14: 0.04 | O14: 0.06 | P14: 0.07 | Q14: 0.08 | R14: 0.1 | S14: 0.1 | T14: 0.11 | U14: 0.1 | V14: 0.1 | W14: 0.08 | X14: 0.06 | Y14: 0.04 | Z14: 0.01 | BJ14: =SUM(L14:BI14) -> 1
A15: =Empreendimentos!B12 -> LT03 | B15: =Empreendimentos!C12 -> Lote misto - Venda | C15: =$C$343 -> Lote aberto | E15: =Empreendimentos!M12 -> 0 | F15: =Empreendimentos!D12 -> 360 | G15: =Empreendimentos!I12 -> 0 | H15: =F15*VLOOKUP(C15,$C$337:$E$344,2,FALSE) -> 432000 | I15: =G15*VLOOKUP(C15,$C$337:$E$344,3,FALSE) -> 0 | J15: =H15/$H$42 -> 0.00038695982 | K15: =I15/$I$47 -> 0 | L15: 1 | BJ15: =SUM(L15:BI15) -> 1
A16: =Empreendimentos!B13 -> LT04 | B16: =Empreendimentos!C13 -> Lote misto - Venda | C16: =$C$343 -> Lote aberto | E16: =Empreendimentos!M13 -> 0 | F16: =Empreendimentos!D13 -> 360 | G16: =Empreendimentos!I13 -> 0 | H16: =F16*VLOOKUP(C16,$C$337:$E$344,2,FALSE) -> 432000 | I16: =G16*VLOOKUP(C16,$C$337:$E$344,3,FALSE) -> 0 | J16: =H16/$H$42 -> 0.00038695982 | K16: =I16/$I$47 -> 0 | L16: 1 | BJ16: =SUM(L16:BI16) -> 1
A17: =Empreendimentos!B14 -> LT05 | B17: =Empreendimentos!C14 -> Lote misto - Venda | C17: =$C$343 -> Lote aberto | E17: =Empreendimentos!M14 -> 0 | F17: =Empreendimentos!D14 -> 360 | G17: =Empreendimentos!I14 -> 0 | H17: =F17*VLOOKUP(C17,$C$337:$E$344,2,FALSE) -> 432000 | I17: =G17*VLOOKUP(C17,$C$337:$E$344,3,FALSE) -> 0 | J17: =H17/$H$42 -> 0.00038695982 | K17: =I17/$I$47 -> 0 | L17: 1 | BJ17: =SUM(L17:BI17) -> 1
A18: =Empreendimentos!B15 -> LT06 | B18: =Empreendimentos!C15 -> Lote misto - Venda | C18: =$C$343 -> Lote aberto | E18: =Empreendimentos!M15 -> 0 | F18: =Empreendimentos!D15 -> 360 | G18: =Empreendimentos!I15 -> 0 | H18: =F18*VLOOKUP(C18,$C$337:$E$344,2,FALSE) -> 432000 | I18: =G18*VLOOKUP(C18,$C$337:$E$344,3,FALSE) -> 0 | J18: =H18/$H$42 -> 0.00038695982 | K18: =I18/$I$47 -> 0 | L18: 1 | BJ18: =SUM(L18:BI18) -> 1
A19: =Empreendimentos!B16 -> LT07 | B19: =Empreendimentos!C16 -> Lote misto - Venda | C19: =$C$343 -> Lote aberto | E19: =Empreendimentos!M16 -> 0 | F19: =Empreendimentos!D16 -> 360 | G19: =Empreendimentos!I16 -> 0 | H19: =F19*VLOOKUP(C19,$C$337:$E$344,2,FALSE) -> 432000 | I19: =G19*VLOOKUP(C19,$C$337:$E$344,3,FALSE) -> 0 | J19: =H19/$H$42 -> 0.00038695982 | K19: =I19/$I$47 -> 0 | L19: 1 | BJ19: =SUM(L19:BI19) -> 1
A20: =Empreendimentos!B17 -> LT08 | B20: =Empreendimentos!C17 -> Lote misto - Venda | C20: =$C$343 -> Lote aberto | E20: =Empreendimentos!M17 -> 0 | F20: =Empreendimentos!D17 -> 360 | G20: =Empreendimentos!I17 -> 0 | H20: =F20*VLOOKUP(C20,$C$337:$E$344,2,FALSE) -> 432000 | I20: =G20*VLOOKUP(C20,$C$337:$E$344,3,FALSE) -> 0 | J20: =H20/$H$42 -> 0.00038695982 | K20: =I20/$I$47 -> 0 | L20: 1 | BJ20: =SUM(L20:BI20) -> 1
A21: =Empreendimentos!B18 -> LT09 | B21: =Empreendimentos!C18 -> Lote misto - Venda | C21: =$C$343 -> Lote aberto | E21: =Empreendimentos!M18 -> 0 | F21: =Empreendimentos!D18 -> 360 | G21: =Empreendimentos!I18 -> 0 | H21: =F21*VLOOKUP(C21,$C$337:$E$344,2,FALSE) -> 432000 | I21: =G21*VLOOKUP(C21,$C$337:$E$344,3,FALSE) -> 0 | J21: =H21/$H$42 -> 0.00038695982 | K21: =I21/$I$47 -> 0 | L21: 1 | BJ21: =SUM(L21:BI21) -> 1
A22: =Empreendimentos!B19 -> LT10 | B22: =Empreendimentos!C19 -> Resid. Multifamiliar | C22: =$C$338 -> Standart Plus | D22: =Empreendimentos!L19 -> 1 | E22: =Empreendimentos!M19 -> 64.614667 | F22: =Empreendimentos!H19 -> 7753.76 | G22: =Empreendimentos!I19 -> 12711.082 | H22: =F22*VLOOKUP(C22,$C$337:$E$344,2,FALSE) -> 62030080 | I22: =G22*VLOOKUP(C22,$C$337:$E$344,3,FALSE) -> 35696308 | J22: =H22/$H$42 -> 0.055562843 | K22: =I22/$I$47 -> 0.057963759 | L22: 0.02 | M22: 0.03 | N22: 0.04 | O22: 0.06 | P22: 0.07 | Q22: 0.08 | R22: 0.1 | S22: 0.1 | T22: 0.11 | U22: 0.1 | V22: 0.1 | W22: 0.08 | X22: 0.06 | Y22: 0.04 | Z22: 0.01 | BJ22: =SUM(L22:BI22) -> 1
A23: =Empreendimentos!B20 -> LT11 | B23: =Empreendimentos!C20 -> Resid. Multifamiliar | C23: =$C$339 -> Médio | D23: =Empreendimentos!L20 -> 1 | E23: =Empreendimentos!M20 -> 70.741333 | F23: =Empreendimentos!H20 -> 8488.96 | G23: =Empreendimentos!I20 -> 13916.328 | H23: =F23*VLOOKUP(C23,$C$337:$E$344,2,FALSE) -> 76400640 | I23: =G23*VLOOKUP(C23,$C$337:$E$344,3,FALSE) -> 42022558 | J23: =H23/$H$42 -> 0.068435133 | K23: =I23/$I$47 -> 0.06823634 | L23: 0.02 | M23: 0.03 | N23: 0.04 | O23: 0.06 | P23: 0.07 | Q23: 0.08 | R23: 0.1 | S23: 0.1 | T23: 0.11 | U23: 0.1 | V23: 0.1 | W23: 0.08 | X23: 0.06 | Y23: 0.04 | Z23: 0.01 | BJ23: =SUM(L23:BI23) -> 1
A24: =Empreendimentos!B21 -> LT12 | B24: =Empreendimentos!C21 -> Lote misto - Venda | C24: =$C$343 -> Lote aberto | D24: =Empreendimentos!L21 -> 0 | E24: =Empreendimentos!M21 -> 0 | F24: =Empreendimentos!D21 -> 360 | G24: =Empreendimentos!I21 -> 0 | H24: =F24*VLOOKUP(C24,$C$337:$E$344,2,FALSE) -> 432000 | I24: =G24*VLOOKUP(C24,$C$337:$E$344,3,FALSE) -> 0 | J24: =H24/$H$42 -> 0.00038695982 | K24: =I24/$I$47 -> 0 | L24: 1 | BJ24: =SUM(L24:BI24) -> 1
A25: =Empreendimentos!B22 -> LT13 | B25: =Empreendimentos!C22 -> Lote misto - Venda | C25: =$C$343 -> Lote aberto | D25: =Empreendimentos!L22 -> 0 | E25: =Empreendimentos!M22 -> 0 | F25: =Empreendimentos!D22 -> 360 | G25: =Empreendimentos!I22 -> 0 | H25: =F25*VLOOKUP(C25,$C$337:$E$344,2,FALSE) -> 432000 | I25: =G25*VLOOKUP(C25,$C$337:$E$344,3,FALSE) -> 0 | J25: =H25/$H$42 -> 0.00038695982 | K25: =I25/$I$47 -> 0 | L25: 1 | BJ25: =SUM(L25:BI25) -> 1
A26: =Empreendimentos!B23 -> LT14 | B26: =Empreendimentos!C23 -> Lote misto - Venda | C26: =$C$343 -> Lote aberto | D26: =Empreendimentos!L23 -> 0 | E26: =Empreendimentos!M23 -> 0 | F26: =Empreendimentos!D23 -> 360 | G26: =Empreendimentos!I23 -> 0 | H26: =F26*VLOOKUP(C26,$C$337:$E$344,2,FALSE) -> 432000 | I26: =G26*VLOOKUP(C26,$C$337:$E$344,3,FALSE) -> 0 | J26: =H26/$H$42 -> 0.00038695982 | K26: =I26/$I$47 -> 0 | L26: 1 | BJ26: =SUM(L26:BI26) -> 1
A27: =Empreendimentos!B24 -> LT15 | B27: =Empreendimentos!C24 -> Lote misto - Venda | C27: =$C$343 -> Lote aberto | D27: =Empreendimentos!L24 -> 0 | E27: =Empreendimentos!M24 -> 0 | F27: =Empreendimentos!D24 -> 360 | G27: =Empreendimentos!I24 -> 0 | H27: =F27*VLOOKUP(C27,$C$337:$E$344,2,FALSE) -> 432000 | I27: =G27*VLOOKUP(C27,$C$337:$E$344,3,FALSE) -> 0 | J27: =H27/$H$42 -> 0.00038695982 | K27: =I27/$I$47 -> 0 | L27: 1 | BJ27: =SUM(L27:BI27) -> 1
A28: =Empreendimentos!B25 -> LT16 | B28: =Empreendimentos!C25 -> Lote misto - Venda | C28: =$C$343 -> Lote aberto | D28: =Empreendimentos!L25 -> 0 | E28: =Empreendimentos!M25 -> 0 | F28: =Empreendimentos!D25 -> 360 | G28: =Empreendimentos!I25 -> 0 | H28: =F28*VLOOKUP(C28,$C$337:$E$344,2,FALSE) -> 432000 | I28: =G28*VLOOKUP(C28,$C$337:$E$344,3,FALSE) -> 0 | J28: =H28/$H$42 -> 0.00038695982 | K28: =I28/$I$47 -> 0 | L28: 1 | BJ28: =SUM(L28:BI28) -> 1
A29: =Empreendimentos!B26 -> LT17 | B29: =Empreendimentos!C26 -> Lote misto - Venda | C29: =$C$343 -> Lote aberto | D29: =Empreendimentos!L26 -> 0 | E29: =Empreendimentos!M26 -> 0 | F29: =Empreendimentos!D26 -> 360 | G29: =Empreendimentos!I26 -> 0 | H29: =F29*VLOOKUP(C29,$C$337:$E$344,2,FALSE) -> 432000 | I29: =G29*VLOOKUP(C29,$C$337:$E$344,3,FALSE) -> 0 | J29: =H29/$H$42 -> 0.00038695982 | K29: =I29/$I$47 -> 0 | L29: 1 | BJ29: =SUM(L29:BI29) -> 1
A30: =Empreendimentos!B27 -> LT18 | B30: =Empreendimentos!C27 -> Lote misto - Venda | C30: =$C$343 -> Lote aberto | D30: =Empreendimentos!L27 -> 0 | E30: =Empreendimentos!M27 -> 0 | F30: =Empreendimentos!D27 -> 360 | G30: =Empreendimentos!I27 -> 0 | H30: =F30*VLOOKUP(C30,$C$337:$E$344,2,FALSE) -> 432000 | I30: =G30*VLOOKUP(C30,$C$337:$E$344,3,FALSE) -> 0 | J30: =H30/$H$42 -> 0.00038695982 | K30: =I30/$I$47 -> 0 | L30: 1 | BJ30: =SUM(L30:BI30) -> 1
A31: =Empreendimentos!B28 -> LT19 | B31: =Empreendimentos!C28 -> Lote misto - Venda | C31: =$C$343 -> Lote aberto | D31: =Empreendimentos!L28 -> 0 | E31: =Empreendimentos!M28 -> 0 | F31: =Empreendimentos!D28 -> 360 | G31: =Empreendimentos!I28 -> 0 | H31: =F31*VLOOKUP(C31,$C$337:$E$344,2,FALSE) -> 432000 | I31: =G31*VLOOKUP(C31,$C$337:$E$344,3,FALSE) -> 0 | J31: =H31/$H$42 -> 0.00038695982 | K31: =I31/$I$47 -> 0 | L31: 1 | BJ31: =SUM(L31:BI31) -> 1
A32: =Empreendimentos!B29 -> LT20 | B32: =Empreendimentos!C29 -> Resid. Multifamiliar | C32: =$C$339 -> Médio | D32: =Empreendimentos!L29 -> 1 | E32: =Empreendimentos!M29 -> 87.25056 | F32: =Empreendimentos!H29 -> 8725.056 | G32: =Empreendimentos!I29 -> 14303.37 | H32: =F32*VLOOKUP(C32,$C$337:$E$344,2,FALSE) -> 78525504 | I32: =G32*VLOOKUP(C32,$C$337:$E$344,3,FALSE) -> 43191294 | J32: =H32/$H$42 -> 0.07033846 | K32: =I32/$I$47 -> 0.070134138 | L32: 0.02 | M32: 0.03 | N32: 0.04 | O32: 0.06 | P32: 0.07 | Q32: 0.08 | R32: 0.1 | S32: 0.1 | T32: 0.11 | U32: 0.1 | V32: 0.1 | W32: 0.08 | X32: 0.06 | Y32: 0.04 | Z32: 0.01 | BJ32: =SUM(L32:BI32) -> 1
A33: =Empreendimentos!B30 -> LT21 | B33: =Empreendimentos!C30 -> Resid. Multifamiliar com fachada ativa | C33: =$C$339 -> Médio | D33: =Empreendimentos!L30 -> 1 | E33: =Empreendimentos!M30 -> 119.265 | F33: =Empreendimentos!H30 -> 11449.44 | G33: =Empreendimentos!I30 -> 18769.574 | H33: =F33*VLOOKUP(C33,$C$337:$E$344,2,FALSE) -> 103044960 | I33: =G33*VLOOKUP(C33,$C$337:$E$344,3,FALSE) -> 56677703 | J33: =H33/$H$42 -> 0.092301525 | K33: =I33/$I$47 -> 0.092033404 | L33: 0.02 | M33: 0.03 | N33: 0.04 | O33: 0.06 | P33: 0.07 | Q33: 0.08 | R33: 0.1 | S33: 0.1 | T33: 0.11 | U33: 0.1 | V33: 0.1 | W33: 0.08 | X33: 0.06 | Y33: 0.04 | Z33: 0.01 | BJ33: =SUM(L33:BI33) -> 1
A34: =Empreendimentos!B31 -> 0 | D34: =Empreendimentos!L31 -> 0 | E34: =Empreendimentos!M31 -> 0 | F34: =Empreendimentos!H31 -> 0 | G34: =Empreendimentos!I31 -> 0 | J34: =H34/$H$42 -> 0 | K34: =I34/$I$47 -> 0 | BJ34: =SUM(L34:BI34) -> 0
A35: =Empreendimentos!B32 -> QC02 | B35: =Empreendimentos!C32 -> Resid. Multifamiliar com fachada ativa | C35: =$C$339 -> Médio | D35: =Empreendimentos!L32 -> 4 | E35: =Empreendimentos!M32 -> 112.06528 | F35: =Empreendimentos!H32 -> 43033.068 | G35: =Empreendimentos!I32 -> 70546.013 | H35: =F35*VLOOKUP(C35,$C$337:$E$344,2,FALSE) -> 387297612 | I35: =G35*VLOOKUP(C35,$C$337:$E$344,3,FALSE) -> 2.1302487e+08 | J35: =H35/$H$42 -> 0.34691809 | K35: =I35/$I$47 -> 0.34591034 | L35: 0.02 | M35: 0.03 | N35: 0.04 | O35: 0.06 | P35: 0.07 | Q35: 0.08 | R35: 0.1 | S35: 0.1 | T35: 0.11 | U35: 0.1 | V35: 0.1 | W35: 0.08 | X35: 0.06 | Y35: 0.04 | Z35: 0.01 | BJ35: =SUM(L35:BI35) -> 1
A36: =Empreendimentos!B33 -> 0 | D36: =Empreendimentos!L33 -> 0 | E36: =Empreendimentos!M33 -> 0 | F36: =Empreendimentos!H33 -> 0 | G36: =Empreendimentos!I33 -> 0 | J36: =H36/$H$42 -> 0 | K36: =I36/$I$47 -> 0 | BJ36: =SUM(L36:BI36) -> 0
A37: =Empreendimentos!B34 -> QC03 | B37: =Empreendimentos!C34 -> Resid. Multifamiliar com fachada ativa | C37: =$C$339 -> Médio | D37: =Empreendimentos!L34 -> 4 | E37: =Empreendimentos!M34 -> 102.3228 | F37: =Empreendimentos!H34 -> 32743.296 | G37: =Empreendimentos!I34 -> 53677.534 | H37: =F37*VLOOKUP(C37,$C$337:$E$344,2,FALSE) -> 294689664 | I37: =G37*VLOOKUP(C37,$C$337:$E$351,3,FALSE) -> 1.6208782e+08 | J37: =H37/$H$42 -> 0.26396541 | K37: =I37/$I$47 -> 0.26319864 | L37: 0.02 | M37: 0.03 | N37: 0.04 | O37: 0.06 | P37: 0.07 | Q37: 0.08 | R37: 0.1 | S37: 0.1 | T37: 0.11 | U37: 0.1 | V37: 0.1 | W37: 0.08 | X37: 0.06 | Y37: 0.04 | Z37: 0.01 | BJ37: =SUM(L37:BI37) -> 1
D38: =Empreendimentos!L35 -> 0 | F38: =Empreendimentos!H35 -> 0 | G38: =Empreendimentos!I35 -> 0 | K38: =I38/$I$47 -> 0 | BJ38: =SUM(L38:BI38) -> 0
B39: Núcleo Recreativo e Cultural | C39: =C349 -> Parque Versailles | D39: =Empreendimentos!L36 -> 0 | E39: =Empreendimentos!M36 -> 0 | F39: =Empreendimentos!H36 -> 0 | G39: =Empreendimentos!D36 -> 17160 | H39: =F39*VLOOKUP(C39,$C$337:$E$351,2,FALSE) -> 0 | I39: =G39*VLOOKUP(C39,$C$337:$E$351,3,FALSE) -> 1029600 | J39: =H39/$H$42 -> 0 | K39: =I39/$I$47 -> 0.0016718672 | L39: 0.5 | M39: 0.5 | BJ39: =SUM(L39:BI39) -> 1
J40: =H40/$H$42 -> 0 | K40: =I40/$H$42 -> 0 | BJ40: =SUM(K40:AI40) -> 0
A42: TOTAL VGV | C42: TOTAIS SIMPLES | H42: =SUM(H12,H35,H37,H39) -> 1116394988 | J42: =SUM(J12,J35,J37) -> 1 | L42: =SUMPRODUCT($H11:$H40,L11:L40) -> 28678300 | M42: =SUMPRODUCT($H11:$H40,M11:M40) -> 33297450 | N42: =SUMPRODUCT($H11:$H40,N11:N40) -> 44396600 | O42: =SUMPRODUCT($H11:$H40,O11:O40) -> 66594899 | P42: =SUMPRODUCT($H11:$H40,P11:P40) -> 77694049 | Q42: =SUMPRODUCT($H11:$H40,Q11:Q40) -> 88793199 | R42: =SUMPRODUCT($H11:$H40,R11:R40) -> 1.109915e+08 | S42: =SUMPRODUCT($H11:$H40,S11:S40) -> 1.109915e+08 | ... BI42: =SUMPRODUCT($H11:$H40,BI11:BI40) -> 0
C43: TOTAIS ACUMULADOS | L43: =L42+J42 -> 28678301 | M43: =M42+L43 -> 61975750 | N43: =N42+M43 -> 1.0637235e+08 | O43: =O42+N43 -> 1.7296725e+08 | P43: =P42+O43 -> 2.506613e+08 | Q43: =Q42+P43 -> 3.394545e+08 | R43: =R42+Q43 -> 4.50446e+08 | S43: =S42+R43 -> 561437495 | T43: =T42+S43 -> 6.8352814e+08 | ... BI43: =BI42+BH43 -> 1116394989
C44: PERCENTUAL MENSAL | L44: =L42/$H$42 -> 0.025688309 | M44: =M42/$H$42 -> 0.029825868 | N44: =N42/$H$42 -> 0.039767824 | O44: =O42/$H$42 -> 0.059651736 | P44: =P42/$H$42 -> 0.069593692 | Q44: =Q42/$H$42 -> 0.079535648 | R44: =R42/$H$42 -> 0.09941956 | S44: =S42/$H$42 -> 0.09941956 | ... BI44: =BI42/$H$42 -> 0
C45: PERCENTUAL ACUMULADO | L45: =L44+K45 -> 0.025688309 | M45: =M44+L45 -> 0.055514177 | N45: =N44+M45 -> 0.095282001 | O45: =O44+N45 -> 0.15493374 | P45: =P44+O45 -> 0.22452743 | Q45: =Q44+P45 -> 0.30406308 | R45: =R44+Q45 -> 0.40348264 | S45: =S44+R45 -> 0.5029022 | ... BI45: =BI44+BH45 -> 1
A47: TOTAL INVESTIMENTOS (OBRAS) | C47: TOTAIS SIMPLES | I47: =SUM(I12,I35,I37,I39) -> 6.1583839e+08 | K47: =SUM(K12,K35,K37,K39) -> 1 | L47: =SUMPRODUCT($I11:$I40,L11:L40) -> 12810976 | M47: =SUMPRODUCT($I11:$I40,M11:M40) -> 18959064 | N47: =SUMPRODUCT($I11:$I40,N11:N40) -> 24592351 | O47: =SUMPRODUCT($I11:$I40,O11:O40) -> 36888527 | P47: =SUMPRODUCT($I11:$I40,P11:P40) -> 43036615 | Q47: =SUMPRODUCT($I11:$I40,Q11:Q40) -> 49184703 | R47: =SUMPRODUCT($I11:$I40,R11:R40) -> 61480879 | S47: =SUMPRODUCT($I11:$I40,S11:S40) -> 61480879 | ... BI47: =SUMPRODUCT($I11:$I40,BI11:BI40) -> 0
C48: TOTAIS ACUMULADOS | L48: =L47 -> 12810976 | M48: =M47+L48 -> 31770039 | N48: =N47+M48 -> 56362391 | O48: =O47+N48 -> 93250918 | P48: =P47+O48 -> 1.3628753e+08 | Q48: =Q47+P48 -> 1.8547224e+08 | R48: =R47+Q48 -> 2.4695311e+08 | S48: =S47+R48 -> 3.0843399e+08 | T48: =T47+S48 -> 3.7606296e+08 | ... BI48: =BI47+BH48 -> 6.1583839e+08
C49: PERCENTUAL MENSAL | L49: =L47/$I$47 -> 0.020802496 | M49: =M47/$I$47 -> 0.030785778 | N49: =N47/$I$47 -> 0.039933125 | O49: =O47/$I$47 -> 0.059899688 | P49: =P47/$I$47 -> 0.069882969 | Q49: =Q47/$I$47 -> 0.079866251 | R49: =R47/$I$47 -> 0.099832813 | S49: =S47/$I$47 -> 0.099832813 | ... BI49: =BI47/$I$47 -> 0
C50: PERCENTUAL ACUMULADO | L50: =L49+K50 -> 0.020802496 | M50: =M49+L50 -> 0.051588274 | N50: =N49+M50 -> 0.091521399 | O50: =O49+N50 -> 0.15142109 | P50: =P49+O50 -> 0.22130406 | Q50: =Q49+P50 -> 0.30117031 | R50: =R49+Q50 -> 0.40100312 | S50: =S49+R50 -> 0.50083593 | ... BI50: =BI49+BH50 -> 1
A53: 2.0 | B53: =Empreendimentos!A41 -> JARDIM CHAMBORD | F53: =F54 -> 128940.25 | G53: =G68 -> 77364.15 | H53: =SUM(H54,H68) -> 296562575 | I53: =SUM(I54,I68) -> 6.0074572e+08 | J53: =H53/$H$83 -> 1 | K53: =I53/$I$88 -> 1 | BJ53: =SUM(L53:BI53) -> 0
A54: =Empreendimentos!B42 -> JC | B54: Loteamento Fechado | F54: =SUM(F55:F66) -> 128940.25 | G54: =SUM(G55:G66) -> 128940.25 | H54: =SUM(H55:H67) -> 296562575 | I54: =SUM(I55:I67) -> 58023112 | J54: =H54/$H$83 -> 1 | K54: =I54/$I$88 -> 0.096585145 | BJ54: =SUM(L54:BI54) -> 0
A55: =Empreendimentos!B43 -> Q01 | B55: =Empreendimentos!C43 -> Residencial unifamiliar | C55: =$C$344 -> Lote Jardins | F55: =Empreendimentos!H43 -> 3016.52 | G55: =F55 -> 3016.52 | H55: =F55*VLOOKUP(C55,$C$337:$E$351,2,FALSE) -> 6937996 | I55: =G55*VLOOKUP(C55,$C$337:$E$344,3,FALSE) -> 1357434 | J55: =H55/$H$83 -> 0.023394712 | K55: =I55/$I$88 -> 0.0022595817 | L55: 0.2 | M55: 0.5 | N55: 0.3 | BJ55: =SUM(L55:BI55) -> 1
A56: =Empreendimentos!B44 -> Q02 | B56: =Empreendimentos!C44 -> Residencial unifamiliar | C56: =$C$344 -> Lote Jardins | F56: =Empreendimentos!H44 -> 13591.31 | G56: =F56 -> 13591.31 | H56: =F56*VLOOKUP(C56,$C$337:$E$344,2,FALSE) -> 31260013 | I56: =G56*VLOOKUP(C56,$C$337:$E$344,3,FALSE) -> 6116089.5 | J56: =H56/$H$83 -> 0.10540781 | K56: =I56/$I$88 -> 0.010180829 | L56: 0.2 | M56: 0.5 | N56: 0.3 | BJ56: =SUM(L56:BI56) -> 1
A57: =Empreendimentos!B45 -> Q03 | B57: =Empreendimentos!C45 -> Residencial unifamiliar | C57: =$C$344 -> Lote Jardins | F57: =Empreendimentos!H45 -> 11309.04 | G57: =F57 -> 11309.04 | H57: =F57*VLOOKUP(C57,$C$337:$E$344,2,FALSE) -> 26010792 | I57: =G57*VLOOKUP(C57,$C$337:$E$344,3,FALSE) -> 5089068 | J57: =H57/$H$83 -> 0.087707601 | K57: =I57/$I$88 -> 0.0084712514 | L57: 0.2 | M57: 0.5 | N57: 0.3 | BJ57: =SUM(L57:BI57) -> 1
A58: =Empreendimentos!B46 -> Q04 | B58: =Empreendimentos!C46 -> Residencial unifamiliar | C58: =$C$344 -> Lote Jardins | F58: =Empreendimentos!H46 -> 13413.04 | G58: =F58 -> 13413.04 | H58: =F58*VLOOKUP(C58,$C$337:$E$344,2,FALSE) -> 30849992 | I58: =G58*VLOOKUP(C58,$C$337:$E$344,3,FALSE) -> 6035868 | J58: =H58/$H$83 -> 0.10402524 | K58: =I58/$I$88 -> 0.010047293 | L58: 0.2 | M58: 0.5 | N58: 0.3 | BJ58: =SUM(L58:BI58) -> 1
A59: =Empreendimentos!B47 -> Q05 | B59: =Empreendimentos!C47 -> Residencial unifamiliar | C59: =$C$344 -> Lote Jardins | F59: =Empreendimentos!H47 -> 9773.57 | G59: =F59 -> 9773.57 | H59: =F59*VLOOKUP(C59,$C$337:$E$344,2,FALSE) -> 22479211 | I59: =G59*VLOOKUP(C59,$C$337:$E$344,3,FALSE) -> 4398106.5 | J59: =H59/$H$83 -> 0.075799217 | K59: =I59/$I$88 -> 0.0073210784 | L59: 0.2 | M59: 0.5 | N59: 0.3 | BJ59: =SUM(L59:BI59) -> 1
A60: =Empreendimentos!B48 -> Q06 | B60: =Empreendimentos!C48 -> Residencial unifamiliar | C60: =$C$344 -> Lote Jardins | F60: =Empreendimentos!H48 -> 4375.69 | G60: =F60 -> 4375.69 | H60: =F60*VLOOKUP(C60,$C$337:$E$344,2,FALSE) -> 10064087 | I60: =G60*VLOOKUP(C60,$C$337:$E$344,3,FALSE) -> 1969060.5 | J60: =H60/$H$83 -> 0.033935796 | K60: =I60/$I$88 -> 0.0032776938 | L60: 0.2 | M60: 0.5 | N60: 0.3 | BJ60: =SUM(L60:BI60) -> 1
A61: =Empreendimentos!B49 -> Q07 | B61: =Empreendimentos!C49 -> Residencial unifamiliar | C61: =$C$344 -> Lote Jardins | F61: =Empreendimentos!H49 -> 8179.16 | G61: =F61 -> 8179.16 | H61: =F61*VLOOKUP(C61,$C$337:$E$344,2,FALSE) -> 18812068 | I61: =G61*VLOOKUP(C61,$C$337:$E$344,3,FALSE) -> 3680622 | J61: =H61/$H$83 -> 0.063433722 | K61: =I61/$I$88 -> 0.0061267553 | L61: 0.2 | M61: 0.5 | N61: 0.3 | BJ61: =SUM(L61:BI61) -> 1
A62: =Empreendimentos!B50 -> Q08 | B62: =Empreendimentos!C50 -> Residencial unifamiliar | C62: =$C$344 -> Lote Jardins | F62: =Empreendimentos!H50 -> 13461.88 | G62: =F62 -> 13461.88 | H62: =F62*VLOOKUP(C62,$C$337:$E$344,2,FALSE) -> 30962324 | I62: =G62*VLOOKUP(C62,$C$337:$E$344,3,FALSE) -> 6057846 | J62: =H62/$H$83 -> 0.10440402 | K62: =I62/$I$88 -> 0.010083877 | L62: 0.2 | M62: 0.5 | N62: 0.3 | BJ62: =SUM(L62:BI62) -> 1
A63: =Empreendimentos!B51 -> Q09 | B63: =Empreendimentos!C51 -> Residencial unifamiliar | C63: =$C$344 -> Lote Jardins | F63: =Empreendimentos!H51 -> 19718.74 | G63: =F63 -> 19718.74 | H63: =F63*VLOOKUP(C63,$C$337:$E$344,2,FALSE) -> 45353102 | I63: =G63*VLOOKUP(C63,$C$337:$E$344,3,FALSE) -> 8873433 | J63: =H63/$H$83 -> 0.15292928 | K63: =I63/$I$88 -> 0.014770697 | L63: 0.2 | M63: 0.5 | N63: 0.3 | BJ63: =SUM(L63:BI63) -> 1
A64: =Empreendimentos!B52 -> Q10 | B64: =Empreendimentos!C52 -> Residencial unifamiliar | C64: =$C$344 -> Lote Jardins | F64: =Empreendimentos!H52 -> 10936.27 | G64: =F64 -> 10936.27 | H64: =F64*VLOOKUP(C64,$C$337:$E$344,2,FALSE) -> 25153421 | I64: =G64*VLOOKUP(C64,$C$337:$E$344,3,FALSE) -> 4921321.5 | J64: =H64/$H$83 -> 0.084816572 | K64: =I64/$I$88 -> 0.0081920209 | L64: 0.2 | M64: 0.5 | N64: 0.3 | BJ64: =SUM(L64:BI64) -> 1
A65: =Empreendimentos!B53 -> Q11 | B65: =Empreendimentos!C53 -> Residencial unifamiliar | C65: =$C$344 -> Lote Jardins | F65: =Empreendimentos!H53 -> 16339.54 | G65: =F65 -> 16339.54 | H65: =F65*VLOOKUP(C65,$C$337:$E$344,2,FALSE) -> 37580942 | I65: =G65*VLOOKUP(C65,$C$337:$E$344,3,FALSE) -> 7352793 | J65: =H65/$H$83 -> 0.1267218 | K65: =I65/$I$88 -> 0.012239443 | L65: 0.2 | M65: 0.5 | N65: 0.3 | BJ65: =SUM(L65:BI65) -> 1
A66: =Empreendimentos!B54 -> Q12 | B66: =Empreendimentos!C54 -> Residencial unifamiliar | C66: =$C$344 -> Lote Jardins | F66: =Empreendimentos!H54 -> 4825.49 | G66: =F66 -> 4825.49 | H66: =F66*VLOOKUP(C66,$C$337:$E$344,2,FALSE) -> 11098627 | I66: =G66*VLOOKUP(C66,$C$337:$E$344,3,FALSE) -> 2171470.5 | J66: =H66/$H$83 -> 0.037424233 | K66: =I66/$I$88 -> 0.003614625 | L66: 0.2 | M66: 0.5 | N66: 0.3 | BJ66: =SUM(L66:BI66) -> 1
J67: =H67/$H$83 -> 0 | K67: =I67/$I$88 -> 0
A68: =Empreendimentos!B42 -> JC | B68: Residências | G68: =SUM(G69:G80) -> 77364.15 | H68: =SUM(H69:H81) -> 0 | I68: =SUM(I69:I81) -> 5.427226e+08 | J68: =H68/$H$83 -> 0 | K68: =I68/$I$88 -> 0.90341485
A69: =Empreendimentos!B43 -> Q01 | B69: =Empreendimentos!C43 -> Residencial unifamiliar | C69: =$C$345 -> Residências | D69: =Empreendimentos!J43 -> 5 | E69: =Empreendimentos!K43 -> 603.304 | G69: =D69*E69*0.6 -> 1809.912 | H69: =F69*VLOOKUP(C69,$C$337:$E$351,2,FALSE) -> 0 | I69: =G69*VLOOKUP(C69,$C$337:$E$351,3,FALSE) -> 12696839 | J69: =H69/$H$83 -> 0 | K69: =I69/$I$88 -> 0.02113513 | N69: 0.05 | O69: 0.06 | P69: 0.08 | Q69: 0.09 | R69: 0.1 | S69: 0.12 | T69: 0.1 | U69: 0.08 | V69: 0.06 | W69: 0.05 | X69: 0.05 | Y69: 0.04 | Z69: 0.04 | AA69: 0.03 | AB69: 0.03 | AC69: 0.02 | BJ69: =SUM(L69:BI69) -> 1
A70: =Empreendimentos!B44 -> Q02 | B70: =Empreendimentos!C44 -> Residencial unifamiliar | C70: =$C$345 -> Residências | D70: =Empreendimentos!J44 -> 22 | E70: =Empreendimentos!K44 -> 617.78682 | G70: =D70*E70*0.6 -> 8154.786 | H70: =F70*VLOOKUP(C70,$C$337:$E$351,2,FALSE) -> 0 | I70: =G70*VLOOKUP(C70,$C$337:$E$351,3,FALSE) -> 57207204 | J70: =H70/$H$83 -> 0 | K70: =I70/$I$88 -> 0.095226986 | N70: 0.05 | O70: 0.06 | P70: 0.08 | Q70: 0.09 | R70: 0.1 | S70: 0.12 | T70: 0.1 | U70: 0.08 | V70: 0.06 | W70: 0.05 | X70: 0.05 | Y70: 0.04 | Z70: 0.04 | AA70: 0.03 | AB70: 0.03 | AC70: 0.02 | BJ70: =SUM(L70:BI70) -> 1
A71: =Empreendimentos!B45 -> Q03 | B71: =Empreendimentos!C45 -> Residencial unifamiliar | C71: =$C$345 -> Residências | D71: =Empreendimentos!J45 -> 18 | E71: =Empreendimentos!K45 -> 628.28 | G71: =D71*E71*0.6 -> 6785.424 | H71: =F71*VLOOKUP(C71,$C$337:$E$351,2,FALSE) -> 0 | I71: =G71*VLOOKUP(C71,$C$337:$E$351,3,FALSE) -> 47600898 | J71: =H71/$H$83 -> 0 | K71: =I71/$I$88 -> 0.07923635 | N71: 0.05 | O71: 0.06 | P71: 0.08 | Q71: 0.09 | R71: 0.1 | S71: 0.12 | T71: 0.1 | U71: 0.08 | V71: 0.06 | W71: 0.05 | X71: 0.05 | Y71: 0.04 | Z71: 0.04 | AA71: 0.03 | AB71: 0.03 | AC71: 0.02 | BJ71: =SUM(L71:BI71) -> 1
A72: =Empreendimentos!B46 -> Q04 | B72: =Empreendimentos!C46 -> Residencial unifamiliar | C72: =$C$345 -> Residências | D72: =Empreendimentos!J46 -> 20 | E72: =Empreendimentos!K46 -> 670.652 | G72: =D72*E72*0.6 -> 8047.824 | H72: =F72*VLOOKUP(C72,$C$337:$E$351,2,FALSE) -> 0 | I72: =G72*VLOOKUP(C72,$C$337:$E$351,3,FALSE) -> 56456847 | J72: =H72/$H$83 -> 0 | K72: =I72/$I$88 -> 0.093977944 | N72: 0.05 | O72: 0.06 | P72: 0.08 | Q72: 0.09 | R72: 0.1 | S72: 0.12 | T72: 0.1 | U72: 0.08 | V72: 0.06 | W72: 0.05 | X72: 0.05 | Y72: 0.04 | Z72: 0.04 | AA72: 0.03 | AB72: 0.03 | AC72: 0.02 | BJ72: =SUM(L72:BI72) -> 1
A73: =Empreendimentos!B47 -> Q05 | B73: =Empreendimentos!C47 -> Residencial unifamiliar | C73: =$C$345 -> Residências | D73: =Empreendimentos!J47 -> 17 | E73: =Empreendimentos!K47 -> 574.91588 | G73: =D73*E73*0.6 -> 5864.142 | H73: =F73*VLOOKUP(C73,$C$337:$E$351,2,FALSE) -> 0 | I73: =G73*VLOOKUP(C73,$C$337:$E$351,3,FALSE) -> 41137949 | J73: =H73/$H$83 -> 0 | K73: =I73/$I$88 -> 0.068478139 | N73: 0.05 | O73: 0.06 | P73: 0.08 | Q73: 0.09 | R73: 0.1 | S73: 0.12 | T73: 0.1 | U73: 0.08 | V73: 0.06 | W73: 0.05 | X73: 0.05 | Y73: 0.04 | Z73: 0.04 | AA73: 0.03 | AB73: 0.03 | AC73: 0.02 | BJ73: =SUM(L73:BI73) -> 1
A74: =Empreendimentos!B48 -> Q06 | B74: =Empreendimentos!C48 -> Residencial unifamiliar | C74: =$C$345 -> Residências | D74: =Empreendimentos!J48 -> 7 | E74: =Empreendimentos!K48 -> 625.09857 | G74: =D74*E74*0.6 -> 2625.414 | H74: =F74*VLOOKUP(C74,$C$337:$E$351,2,FALSE) -> 0 | I74: =G74*VLOOKUP(C74,$C$337:$E$351,3,FALSE) -> 18417724 | J74: =H74/$H$83 -> 0 | K74: =I74/$I$88 -> 0.030658102 | N74: 0.05 | O74: 0.06 | P74: 0.08 | Q74: 0.09 | R74: 0.1 | S74: 0.12 | T74: 0.1 | U74: 0.08 | V74: 0.06 | W74: 0.05 | X74: 0.05 | Y74: 0.04 | Z74: 0.04 | AA74: 0.03 | AB74: 0.03 | AC74: 0.02 | BJ74: =SUM(L74:BI74) -> 1
A75: =Empreendimentos!B49 -> Q07 | B75: =Empreendimentos!C49 -> Residencial unifamiliar | C75: =$C$345 -> Residências | D75: =Empreendimentos!J49 -> 12 | E75: =Empreendimentos!K49 -> 681.59667 | G75: =D75*E75*0.6 -> 4907.496 | H75: =F75*VLOOKUP(C75,$C$337:$E$351,2,FALSE) -> 0 | I75: =G75*VLOOKUP(C75,$C$337:$E$351,3,FALSE) -> 34426915 | J75: =H75/$H$83 -> 0 | K75: =I75/$I$88 -> 0.057306967 | N75: 0.05 | O75: 0.06 | P75: 0.08 | Q75: 0.09 | R75: 0.1 | S75: 0.12 | T75: 0.1 | U75: 0.08 | V75: 0.06 | W75: 0.05 | X75: 0.05 | Y75: 0.04 | Z75: 0.04 | AA75: 0.03 | AB75: 0.03 | AC75: 0.02 | BJ75: =SUM(L75:BI75) -> 1
A76: =Empreendimentos!B50 -> Q08 | B76: =Empreendimentos!C50 -> Residencial unifamiliar | C76: =$C$345 -> Residências | D76: =Empreendimentos!J50 -> 23 | E76: =Empreendimentos!K50 -> 585.29913 | G76: =D76*E76*0.6 -> 8077.128 | H76: =F76*VLOOKUP(C76,$C$337:$E$351,2,FALSE) -> 0 | I76: =G76*VLOOKUP(C76,$C$337:$E$351,3,FALSE) -> 56662420 | J76: =H76/$H$83 -> 0 | K76: =I76/$I$88 -> 0.094320139 | N76: 0.05 | O76: 0.06 | P76: 0.08 | Q76: 0.09 | R76: 0.1 | S76: 0.12 | T76: 0.1 | U76: 0.08 | V76: 0.06 | W76: 0.05 | X76: 0.05 | Y76: 0.04 | Z76: 0.04 | AA76: 0.03 | AB76: 0.03 | AC76: 0.02 | BJ76: =SUM(L76:BI76) -> 1
A77: =Empreendimentos!B51 -> Q09 | B77: =Empreendimentos!C51 -> Residencial unifamiliar | C77: =$C$345 -> Residências | D77: =Empreendimentos!J51 -> 35 | E77: =Empreendimentos!K51 -> 563.39257 | G77: =D77*E77*0.6 -> 11831.244 | H77: =F77*VLOOKUP(C77,$C$337:$E$351,2,FALSE) -> 0 | I77: =G77*VLOOKUP(C77,$C$337:$E$351,3,FALSE) -> 82998179 | J77: =H77/$H$83 -> 0 | K77: =I77/$I$88 -> 0.13815859 | N77: 0.05 | O77: 0.06 | P77: 0.08 | Q77: 0.09 | R77: 0.1 | S77: 0.12 | T77: 0.1 | U77: 0.08 | V77: 0.06 | W77: 0.05 | X77: 0.05 | Y77: 0.04 | Z77: 0.04 | AA77: 0.03 | AB77: 0.03 | AC77: 0.02 | BJ77: =SUM(L77:BI77) -> 1
A78: =Empreendimentos!B52 -> Q10 | B78: =Empreendimentos!C52 -> Residencial unifamiliar | C78: =$C$345 -> Residências | D78: =Empreendimentos!J52 -> 17 | E78: =Empreendimentos!K52 -> 643.31 | G78: =D78*E78*0.6 -> 6561.762 | H78: =F78*VLOOKUP(C78,$C$337:$E$351,2,FALSE) -> 0 | I78: =G78*VLOOKUP(C78,$C$337:$E$351,3,FALSE) -> 46031871 | J78: =H78/$H$83 -> 0 | K78: =I78/$I$88 -> 0.076624551 | N78: 0.05 | O78: 0.06 | P78: 0.08 | Q78: 0.09 | R78: 0.1 | S78: 0.12 | T78: 0.1 | U78: 0.08 | V78: 0.06 | W78: 0.05 | X78: 0.05 | Y78: 0.04 | Z78: 0.04 | AA78: 0.03 | AB78: 0.03 | AC78: 0.02 | BJ78: =SUM(L78:BI78) -> 1
A79: =Empreendimentos!B53 -> Q11 | B79: =Empreendimentos!C53 -> Residencial unifamiliar | C79: =$C$345 -> Residências | D79: =Empreendimentos!J53 -> 25 | E79: =Empreendimentos!K53 -> 653.5816 | G79: =D79*E79*0.6 -> 9803.724 | H79: =F79*VLOOKUP(C79,$C$337:$E$351,2,FALSE) -> 0 | I79: =G79*VLOOKUP(C79,$C$337:$E$351,3,FALSE) -> 68774783 | J79: =H79/$H$83 -> 0 | K79: =I79/$I$88 -> 0.11448235 | N79: 0.05 | O79: 0.06 | P79: 0.08 | Q79: 0.09 | R79: 0.1 | S79: 0.12 | T79: 0.1 | U79: 0.08 | V79: 0.06 | W79: 0.05 | X79: 0.05 | Y79: 0.04 | Z79: 0.04 | AA79: 0.03 | AB79: 0.03 | AC79: 0.02 | BJ79: =SUM(L79:BI79) -> 1
A80: =Empreendimentos!B54 -> Q12 | B80: =Empreendimentos!C54 -> Residencial unifamiliar | C80: =$C$345 -> Residências | D80: =Empreendimentos!J54 -> 7 | E80: =Empreendimentos!K54 -> 689.35571 | G80: =D80*E80*0.6 -> 2895.294 | H80: =F80*VLOOKUP(C80,$C$337:$E$351,2,FALSE) -> 0 | I80: =G80*VLOOKUP(C80,$C$337:$E$351,3,FALSE) -> 20310977 | J80: =H80/$H$83 -> 0 | K80: =I80/$I$88 -> 0.033809608 | N80: 0.05 | O80: 0.06 | P80: 0.08 | Q80: 0.09 | R80: 0.1 | S80: 0.12 | T80: 0.1 | U80: 0.08 | V80: 0.06 | W80: 0.05 | X80: 0.05 | Y80: 0.04 | Z80: 0.04 | AA80: 0.03 | AB80: 0.03 | AC80: 0.02 | BJ80: =SUM(L80:BI80) -> 1
J81: =H81/$H$42 -> 0 | K81: =I81/$H$42 -> 0 | BJ81: =SUM(K81:AI81) -> 0
A83: TOTAL VGV | C83: TOTAIS SIMPLES | H83: =SUM(H68,H54) -> 296562575 | J83: =SUM(J68,J54) -> 1 | L83: =SUMPRODUCT($H54:$H81,L54:L81) -> 59312515 | M83: =SUMPRODUCT($H54:$H81,M54:M81) -> 1.4828129e+08 | N83: =SUMPRODUCT($H54:$H81,N54:N81) -> 88968772 | O83: =SUMPRODUCT($H54:$H81,O54:O81) -> 0 | P83: =SUMPRODUCT($H54:$H81,P54:P81) -> 0 | Q83: =SUMPRODUCT($H54:$H81,Q54:Q81) -> 0 | R83: =SUMPRODUCT($H54:$H81,R54:R81) -> 0 | S83: =SUMPRODUCT($H54:$H81,S54:S81) -> 0 | ... BI83: =SUMPRODUCT($H54:$H81,BI54:BI81) -> 0
C84: TOTAIS ACUMULADOS | L84: =L83+K84 -> 59312515 | M84: =M83+L84 -> 2.075938e+08 | N84: =N83+M84 -> 296562575 | O84: =O83+N84 -> 296562575 | P84: =P83+O84 -> 296562575 | Q84: =Q83+P84 -> 296562575 | R84: =R83+Q84 -> 296562575 | S84: =S83+R84 -> 296562575 | ... BI84: =BI83+BH84 -> 296562575
C85: PERCENTUAL MENSAL | L85: =L83/$H$83 -> 0.2 | M85: =M83/$H$83 -> 0.5 | N85: =N83/$H$83 -> 0.3 | O85: =O83/$H$83 -> 0 | P85: =P83/$H$83 -> 0 | Q85: =Q83/$H$83 -> 0 | R85: =R83/$H$83 -> 0 | S85: =S83/$H$83 -> 0 | ... BI85: =BI83/$H$83 -> 0
C86: PERCENTUAL ACUMULADO | L86: =L85+K86 -> 0.2 | M86: =M85+L86 -> 0.7 | N86: =N85+M86 -> 1 | O86: =O85+N86 -> 1 | P86: =P85+O86 -> 1 | Q86: =Q85+P86 -> 1 | R86: =R85+Q86 -> 1 | S86: =S85+R86 -> 1 | ... BI86: =BI85+BH86 -> 1
A88: TOTAL INVESTIMENTOS (OBRAS) | C88: TOTAIS SIMPLES | I88: =SUM(I68,I54) -> 6.0074572e+08 | K88: =SUM(K68,K54) -> 1 | L88: =SUMPRODUCT($I54:$I81,L54:L81) -> 11604623 | M88: =SUMPRODUCT($I54:$I81,M54:M81) -> 29011556 | N88: =SUMPRODUCT($I54:$I81,N54:N81) -> 44543064 | O88: =SUMPRODUCT($I54:$I81,O54:O81) -> 32563356 | P88: =SUMPRODUCT($I54:$I81,P54:P81) -> 43417808 | Q88: =SUMPRODUCT($I54:$I81,Q54:Q81) -> 48845034 | R88: =SUMPRODUCT($I54:$I81,R54:R81) -> 54272260 | S88: =SUMPRODUCT($I54:$I81,S54:S81) -> 65126713 | ... BI88: =SUMPRODUCT($I54:$I81,BI54:BI81) -> 0
C89: TOTAIS ACUMULADOS | L89: =L88+K88 -> 11604624 | M89: =M88+L89 -> 40616180 | N89: =N88+M89 -> 85159244 | O89: =O88+N89 -> 1.177226e+08 | P89: =P88+O89 -> 1.6114041e+08 | Q89: =Q88+P89 -> 2.0998544e+08 | R89: =R88+Q89 -> 2.642577e+08 | S89: =S88+R89 -> 3.2938442e+08 | T89: =T88+S89 -> 3.8365668e+08 | ... BI89: =BI88+BH89 -> 6.0074572e+08
C90: PERCENTUAL MENSAL | L90: =L88/$I$88 -> 0.019317029 | M90: =M88/$I$88 -> 0.048292573 | N90: =N88/$I$88 -> 0.074146286 | O90: =O88/$I$88 -> 0.054204891 | P90: =P88/$I$88 -> 0.072273188 | Q90: =Q88/$I$88 -> 0.081307337 | R90: =R88/$I$88 -> 0.090341485 | S90: =S88/$I$88 -> 0.10840978 | ... BI90: =BI88/$I$88 -> 0
C91: PERCENTUAL ACUMULADO | L91: =L90 -> 0.019317029 | M91: =M90+L91 -> 0.067609602 | N91: =N90+M91 -> 0.14175589 | O91: =O90+N91 -> 0.19596078 | P91: =P90+O91 -> 0.26823397 | Q91: =Q90+P91 -> 0.3495413 | R91: =R90+Q91 -> 0.43988279 | S91: =S90+R91 -> 0.54829257 | T91: =T90+S91 -> 0.63863406 | ... BI91: =BI90+BH91 -> 1
A94: 3.0 | B94: =Empreendimentos!A57 -> AL'DORA TOWN | F94: =SUM(F95,F99,F103,F109,F113) -> 220220.09 | G94: =SUM(G95,G99,G103,G109,G113) -> 489891.8 | H94: =SUM(H95,H99,H103,H109,H113) -> 1.7093334e+09 | I94: =SUM(I95,I99,I103,I109,I113) -> 1.0873541e+09 | J94: =H94/$H$118 -> 1 | K94: =I94/$I$123 -> 1 | BJ94: =SUM(L94:BI94) -> 0
A95: =Empreendimentos!B58 -> QAT01 | B95: =Empreendimentos!C58 -> Residencial multifamiliar | F95: =SUM(F96:F97) -> 55488.593 | G95: =SUM(G96:G97) -> 83252.665 | H95: =SUM(H96:H98) -> 3.908327e+08 | I95: =SUM(I96:I98) -> 2.1798495e+08 | J95: =H95/$H$118 -> 0.22864626 | K95: =I95/$I$123 -> 0.20047283 | BJ95: =SUM(L95:BI95) -> 0
A96: =Empreendimentos!B84 -> 0 | B96: =Empreendimentos!C58 -> Residencial multifamiliar | C96: =$C$339 -> Médio | D96: =Empreendimentos!L58 -> 4 | E96: =Empreendimentos!M58 -> 104.38908 | F96: =Empreendimentos!H58 -> 43425.856 | G96: =Empreendimentos!I58 -> 71189.927 | H96: =F96*VLOOKUP(C96,$C$337:$E$351,2,FALSE) -> 3.908327e+08 | I96: =G96*VLOOKUP(C96,$C$337:$E$344,3,FALSE) -> 2.1496927e+08 | J96: =H96/$H$118 -> 0.22864626 | K96: =I96/$I$123 -> 0.19769941 | M96: ='Cronogramaa Fisico'!E20 -> 0 | N96: ='Cronogramaa Fisico'!F20 -> 0.02 | O96: ='Cronogramaa Fisico'!G20 -> 0.03 | P96: ='Cronogramaa Fisico'!H20 -> 0.04 | Q96: ='Cronogramaa Fisico'!I20 -> 0.06 | R96: ='Cronogramaa Fisico'!J20 -> 0.07 | S96: ='Cronogramaa Fisico'!K20 -> 0.08 | T96: ='Cronogramaa Fisico'!L20 -> 0.1 | ... AI96: ='Cronogramaa Fisico'!AA20 -> 0 | BJ96: =SUM(L96:BI96) -> 1
B97: Infra estrutura | C97: =$C$343 -> Lote aberto | D97: =Empreendimentos!L58 -> 4 | E97: =Empreendimentos!K58 -> 3015.6844 | F97: =Empreendimentos!D58 -> 12062.738 | G97: =F97 -> 12062.738 | I97: =G97*VLOOKUP(C97,$C$337:$E$344,3,FALSE) -> 3015684.4 | J97: =H97/$H$118 -> 0 | K97: =I97/$I$123 -> 0.0027734152 | L97: ='Cronogramaa Fisico'!$D$17 -> 0 | M97: ='Cronogramaa Fisico'!E17 -> 0.4 | N97: ='Cronogramaa Fisico'!F17 -> 0.6 | O97: ='Cronogramaa Fisico'!G17 -> 0 | P97: ='Cronogramaa Fisico'!H17 -> 0 | Q97: ='Cronogramaa Fisico'!I17 -> 0 | R97: ='Cronogramaa Fisico'!J17 -> 0 | S97: ='Cronogramaa Fisico'!K17 -> 0 | T97: ='Cronogramaa Fisico'!L17 -> 0 | ... AI97: ='Cronogramaa Fisico'!AA17 -> 0 | BJ97: =SUM(L97:BI97) -> 1
J98: =H98/$H$118 -> 0 | K98: =I98/$I$123 -> 0
A99: =Empreendimentos!B60 -> QAT02 | B99: Mall | F99: =SUM(F100:F101) -> 7140.064 | G99: =SUM(G100:G101) -> 17850.16 | H99: =SUM(H100:H101) -> 71400640 | I99: =SUM(I100:I101) -> 37039082 | J99: =H99/$H$118 -> 0.041771043 | K99: =I99/$I$123 -> 0.034063496
A100: =Empreendimentos!B88 -> 0 | B100: =Empreendimentos!C60 -> Mall | C100: =$C$346 -> Mall | F100: =Empreendimentos!H60 -> 7140.064 | G100: =Empreendimentos!I60 -> 8925.08 | H100: =F100*VLOOKUP(C100,$C$337:$E$351,2,FALSE) -> 71400640 | I100: =G100*VLOOKUP(C100,$C$337:$E$351,3,FALSE) -> 34807812 | J100: =H100/$H$118 -> 0.041771043 | K100: =I100/$I$123 -> 0.032011478 | M100: ='Cronogramaa Fisico'!E18 -> 0 | N100: ='Cronogramaa Fisico'!F18 -> 0.2 | O100: ='Cronogramaa Fisico'!G18 -> 0.4 | P100: ='Cronogramaa Fisico'!H18 -> 0 | Q100: ='Cronogramaa Fisico'!I18 -> 0 | R100: ='Cronogramaa Fisico'!J18 -> 0 | S100: ='Cronogramaa Fisico'!K18 -> 0 | T100: ='Cronogramaa Fisico'!L18 -> 0.2 | ... AH100: ='Cronogramaa Fisico'!Z18 -> 0 | BJ100: =SUM(L100:BI100) -> 1
B101: Infra estrutura | C101: =$C$343 -> Lote aberto | G101: =Empreendimentos!D60 -> 8925.08 | I101: =G101*VLOOKUP(C101,$C$337:$E$351,3,FALSE) -> 2231270 | J101: =H101/$H$118 -> 0 | K101: =I101/$I$123 -> 0.0020520178 | L101: =L97 -> 0 | M101: =M97 -> 0.4 | N101: =N97 -> 0.6 | O101: =O97 -> 0 | P101: =P97 -> 0 | Q101: =Q97 -> 0 | R101: =R97 -> 0 | S101: =S97 -> 0 | ... AI101: =AI97 -> 0 | BJ101: =SUM(L101:BI101) -> 1
J102: =H102/$H$118 -> 0 | K102: =I102/$I$123 -> 0
A103: =Empreendimentos!B62 -> QAT03 | B103: Misto | D103: =Empreendimentos!L62 -> 4 | E103: =Empreendimentos!D62 -> 15349.12 | F103: =Empreendimentos!H62 -> 55256.832 | G103: =Empreendimentos!I62 -> 221027.33 | H103: =SUM(H104:H107) -> 2.5342148e+08 | I103: =SUM(I104:I107) -> 1.5282986e+08 | J103: =H103/$H$118 -> 0.14825749 | K103: =I103/$I$123 -> 0.14055206
A104: =Empreendimentos!B86 -> 0 | B104: =Empreendimentos!C63 -> Escola Infantil | C104: =$C$348 -> Escola | D104: =Empreendimentos!L63 -> 1 | E104: =Empreendimentos!D63 -> 3514.04 | G104: =Empreendimentos!I63 -> 1909.47 | H104: =F104*VLOOKUP(C104,$C$337:$E$351,2,FALSE) -> 0 | I104: =G104*VLOOKUP(C104,$C$337:$E$351,3,FALSE) -> 6587671.5 | J104: =H104/$H$118 -> 0 | K104: =I104/$I$123 -> 0.0060584417 | M104: ='Cronogramaa Fisico'!E19 -> 0 | N104: ='Cronogramaa Fisico'!F19 -> 0.2 | O104: ='Cronogramaa Fisico'!G19 -> 0.3 | P104: ='Cronogramaa Fisico'!H19 -> 0 | Q104: ='Cronogramaa Fisico'!I19 -> 0 | R104: ='Cronogramaa Fisico'!J19 -> 0 | S104: ='Cronogramaa Fisico'!K19 -> 0 | T104: ='Cronogramaa Fisico'!L19 -> 0.1 | ... AE104: ='Cronogramaa Fisico'!W19 -> 0 | BJ104: =SUM(L104:BI104) -> 1
B105: =Empreendimentos!C64 -> Escola Fundamental | C105: =$C$348 -> Escola | D105: =Empreendimentos!L64 -> 1 | E105: =Empreendimentos!D64 -> 3607.11 | G105: =Empreendimentos!I64 -> 1710.59 | H105: =F105*VLOOKUP(C105,$C$337:$E$351,2,FALSE) -> 0 | I105: =G105*VLOOKUP(C105,$C$337:$E$351,3,FALSE) -> 5901535.5 | J105: =H105/$H$118 -> 0 | K105: =I105/$I$123 -> 0.0054274274 | M105: ='Cronogramaa Fisico'!E19 -> 0 | N105: ='Cronogramaa Fisico'!F19 -> 0.2 | O105: ='Cronogramaa Fisico'!G19 -> 0.3 | P105: ='Cronogramaa Fisico'!H19 -> 0 | Q105: ='Cronogramaa Fisico'!I19 -> 0 | R105: ='Cronogramaa Fisico'!J19 -> 0 | S105: ='Cronogramaa Fisico'!K19 -> 0 | T105: ='Cronogramaa Fisico'!L19 -> 0.1 | ... AE105: ='Cronogramaa Fisico'!W19 -> 0 | BJ105: =SUM(L105:BI105) -> 1
B106: =Empreendimentos!C65 -> Corporativo | C106: =$C$342 -> Coorporativo | D106: =Empreendimentos!L65 -> 2 | E106: =Empreendimentos!D65 -> 8227.97 | F106: =Empreendimentos!H65 -> 18101.534 | G106: =Empreendimentos!I65 -> 29674.646 | H106: =F106*VLOOKUP(C106,$C$337:$E$351,2,FALSE) -> 2.5342148e+08 | I106: =G106*VLOOKUP(C106,$C$337:$E$351,3,FALSE) -> 1.3650337e+08 | J106: =H106/$H$118 -> 0.14825749 | K106: =I106/$I$123 -> 0.12553718 | M106: =M96 -> 0 | N106: =N96 -> 0.02 | O106: =O96 -> 0.03 | P106: =P96 -> 0.04 | Q106: =Q96 -> 0.06 | R106: =R96 -> 0.07 | S106: =S96 -> 0.08 | T106: =T96 -> 0.1 | ... AG106: =AG96 -> 0 | BJ106: =SUM(L106:BI106) -> 1
B107: Infra estrutura | C107: =$C$343 -> Lote aberto | G107: =Empreendimentos!D62 -> 15349.12 | I107: =G107*VLOOKUP(C107,$C$337:$E$351,3,FALSE) -> 3837280 | J107: =H107/$H$118 -> 0 | K107: =I107/$I$123 -> 0.0035290068 | L107: =L97 -> 0 | M107: =M97 -> 0.4 | N107: =N97 -> 0.6 | O107: =O97 -> 0 | P107: =P97 -> 0 | Q107: =Q97 -> 0 | R107: =R97 -> 0 | S107: =S97 -> 0 | ... U107: =U97 -> 0 | BJ107: =SUM(L107:BI107) -> 1
J108: =H108/$H$118 -> 0 | K108: =I108/$I$123 -> 0
A109: =Empreendimentos!B67 -> QAT04 | B109: =Empreendimentos!C67 -> Residencial | D109: =SUM(D110:D111) -> 4 | E109: =Empreendimentos!M67 -> 223.95694 | F109: =Empreendimentos!H67 -> 42999.732 | G109: =Empreendimentos!I67 -> 70491.364 | H109: =SUM(H110:H111) -> 4.2999732e+08 | I109: =SUM(I110:I111) -> 2.9353978e+08 | J109: =H109/$H$118 -> 0.25155848 | K109: =I109/$I$123 -> 0.26995786
B110: =Empreendimentos!C67 -> Residencial | C110: =$C$341 -> Super Luxo | D110: =Empreendimentos!L67 -> 4 | E110: =Empreendimentos!M67 -> 223.95694 | F110: =Empreendimentos!H67 -> 42999.732 | G110: =Empreendimentos!I67 -> 70491.364 | H110: =F110*VLOOKUP(C110,$C$337:$E$351,2,FALSE) -> 4.2999732e+08 | I110: =G110*VLOOKUP(C110,$C$337:$E$351,3,FALSE) -> 2.9055369e+08 | J110: =H110/$H$118 -> 0.25155848 | K110: =I110/$I$123 -> 0.26721166 | M110: =M96 -> 0 | N110: =N96 -> 0.02 | O110: =O96 -> 0.03 | P110: =P96 -> 0.04 | Q110: =Q96 -> 0.06 | R110: =R96 -> 0.07 | S110: =S96 -> 0.08 | T110: =T96 -> 0.1 | ... AH110: =AH96 -> 0 | BJ110: =SUM(L110:BI110) -> 1
B111: Infra estrutura | C111: =$C$343 -> Lote aberto | G111: =Empreendimentos!D67 -> 11944.37 | I111: =G111*VLOOKUP(C111,$C$337:$E$351,3,FALSE) -> 2986092.5 | J111: =H111/$H$118 -> 0 | K111: =I111/$I$123 -> 0.0027462006 | L111: =L97 -> 0 | M111: =M97 -> 0.4 | N111: =N97 -> 0.6 | O111: =O97 -> 0 | P111: =P97 -> 0 | Q111: =Q97 -> 0 | R111: =R97 -> 0 | S111: =S97 -> 0 | T111: =T97 -> 0 | BJ111: =SUM(L111:BI111) -> 1
...

Sheet GRAFICOS
B1: 1° ano | C1: 2° ano | D1: 3° ano | E1: 4° ano | F1: 5° ano | G1: 6° ano | H1: 7° ano | I1: 8° ano | J1: 9° ano | K1: 10° ano | L1: 11° ano | M1: 12° ano | N1: 13° ano | O1: 14° ano | P1: 15° ano | Q1: 16° ano | R1: 17° ano | S1: 18° ano | T1: 19° ano | U1: 20° ano
B2: 2026 | C2: 2027 | D2: 2028 | E2: 2029 | F2: 2030 | G2: 2031 | H2: 2032 | I2: 2033 | J2: 2034 | K2: 2035 | L2: 2036 | M2: 2037 | N2: 2038 | O2: 2039 | P2: 2040 | Q2: 2041 | R2: 2042 | S2: 2043 | T2: 2044 | U2: 2045
A3: VGV ANUAL | B3: ='Cromograma Fisico Financeiro'!L323/1000000000 -> 0.087990815 | C3: ='Cromograma Fisico Financeiro'!M323/1000000000 -> 0.23198899 | D3: ='Cromograma Fisico Financeiro'!N323/1000000000 -> 0.30265481 | E3: ='Cromograma Fisico Financeiro'!O323/1000000000 -> 0.2988923 | F3: ='Cromograma Fisico Financeiro'!P323/1000000000 -> 0.31209728 | G3: ='Cromograma Fisico Financeiro'!Q323/1000000000 -> 0.21227429 | H3: ='Cromograma Fisico Financeiro'!R323/1000000000 -> 0.28733944 | I3: ='Cromograma Fisico Financeiro'!S323/1000000000 -> 0.39925377 | ... U3: ='Cromograma Fisico Financeiro'!AE323/1000000000 -> 0.28783704
A4: VGV ACUMULADO | B4: ='Cromograma Fisico Financeiro'!L324/1000000000 -> 0.087990815 | C4: ='Cromograma Fisico Financeiro'!M324/1000000000 -> 0.31997981 | D4: ='Cromograma Fisico Financeiro'!N324/1000000000 -> 0.62263461 | E4: ='Cromograma Fisico Financeiro'!O324/1000000000 -> 0.92152691 | F4: ='Cromograma Fisico Financeiro'!P324/1000000000 -> 1.2336242 | G4: ='Cromograma Fisico Financeiro'!Q324/1000000000 -> 1.4458985 | H4: ='Cromograma Fisico Financeiro'!R324/1000000000 -> 1.7332379 | I4: ='Cromograma Fisico Financeiro'!S324/1000000000 -> 2.1324917 | ... U4: ='Cromograma Fisico Financeiro'!AE324/1000000000 -> 6.7973715
B39: 1° ano | C39: 5° ano | D39: 10° ano | E39: 20° ano
B40: 2026 | C40: =F2 -> 2030 | D40: =K2 -> 2035 | E40: =U2 -> 2045
A41: EMPREGOS ANUAL | B41: 2200 | C41: =31000-2000 -> 29000 | D41: =75200-29000 -> 46200 | E41: =170000-46200 -> 123800
A42: EMPREGOS ACUMULADO | B42: =B41 -> 2200 | C42: =B41+C41 -> 31200 | D42: =C41+D41 -> 75200 | E42: =D41+E41 -> 170000
B65: 1° ano | C65: 2° ano | D65: 3° ano | E65: 4° ano | F65: 5° ano | G65: 6° ano | H65: 7° ano | I65: 8° ano | J65: 9° ano | K65: 10° ano | L65: 11° ano | M65: 12° ano | N65: 13° ano | O65: 14° ano | P65: 15° ano | Q65: 16° ano | R65: 17° ano | S65: 18° ano | T65: 19° ano | U65: 20° ano
B66: 2026 | C66: 2027 | D66: 2028 | E66: 2029 | F66: 2030 | G66: 2031 | H66: 2032 | I66: 2033 | J66: 2034 | K66: 2035 | L66: 2036 | M66: 2037 | N66: 2038 | O66: 2039 | P66: 2040 | Q66: 2041 | R66: 2042 | S66: 2043 | T66: 2044 | U66: 2045
A67: INVESTIMENTOS ANUAL | B67: ='Cromograma Fisico Financeiro'!L328/1000000000 -> 0.024415598 | C67: ='Cromograma Fisico Financeiro'!M328/1000000000 -> 0.087573681 | D67: ='Cromograma Fisico Financeiro'!N328/1000000000 -> 0.16676675 | E67: ='Cromograma Fisico Financeiro'!O328/1000000000 -> 0.19298122 | F67: ='Cromograma Fisico Financeiro'!P328/1000000000 -> 0.19030309 | G67: ='Cromograma Fisico Financeiro'!Q328/1000000000 -> 0.20364209 | H67: ='Cromograma Fisico Financeiro'!R328/1000000000 -> 0.25844996 | I67: ='Cromograma Fisico Financeiro'!S328/1000000000 -> 0.28666898 | ... U67: ='Cromograma Fisico Financeiro'!AE328/1000000000 -> 0.26395422
A68: INVESTIMENTOS ACUM. | B68: =B67 -> 0.024415598 | C68: =B68+C67 -> 0.11198928 | D68: =C68+D67 -> 0.27875603 | E68: =D68+E67 -> 0.47173725 | F68: =E68+F67 -> 0.66204034 | G68: =F68+G67 -> 0.86568244 | H68: =G68+H67 -> 1.1241324 | I68: =H68+I67 -> 1.4108014 | J68: =I68+J67 -> 1.7428769 | ... U68: =T68+U67 -> 5.3196572

Sheet QUADRO DE ÁREAS e POPULAÇÃO
A1: ALDORA BOULEVARD
A3: Área Total | B3: 59743.74 | C3: 1 | F3: CALCULO CONFORME INDICE PREFEITURA
A4: Área Parcelável | B4: =B3 -> 59743.74 | C4: =B4/B3 -> 1 | F4: Área Líquida | G4: CA | H4: Área Construtiva | I4: Apartamento Padrão | J4: Nº de Apartamentos | K4: Morador por Domicílio (IBGE) | L4: População Prevista | M4: Densidade Líquida | P4: População Prevista
E5: Indice 4 | F5: =B8 -> 37412.41 | G5: 4 | H5: =G5*F5 -> 149649.64 | I5: 100 | J5: =H5/I5 -> 1496.4964 | K5: 2.8 | L5: =K5*J5 -> 4190.1899 | M5: =L5/F5*10000 -> 1120 | P5: =L5 -> 4190.1899
A6: Área a Parcelar | B6: =B4 -> 59743.74 | C6: 1
A7: Área Alienável | B7: =B8+B9 -> 42812.41 | C7: =B7/B6 -> 0.71660077 | F7: CALCULO COM DENSIDADE SUGERIDA
A8: Lotes Residenciais | B8: 37412.41 | C8: =B8/B6 -> 0.62621473 | F8: Densidade Líquida | G8: Área Habitacional Total | I8: População Prevista | J8: Morador por Domicílio (IBGE) | K8: Nº de Apartamentos | L8: Apartamento Padrão | M8: Área Construtiva | N8: CA
A9: Lotes Comerciais | B9: 5400 | C9: =B9/B6 -> 0.090386039 | F9: 600 | G9: =B8/10000 -> 3.741241 | I9: =G9*F9 -> 2244.7446 | J9: 2.8 | K9: =I9/J9 -> 801.6945 | L9: 100 | M9: =K9*L9 -> 80169.45 | N9: =(M9/G9)/10000 -> 2.1428571
A10: Área Verde | B10: 7741.42 | C10: =B10/B6 -> 0.12957709
A11: Sistema Viário | B11: =B6-B7-B10 -> 9189.91 | C11: =B11/B6 -> 0.15382214
A14: ALDORA TOWN
A16: Área Total | B16: 117208.4 | C16: 1 | F16: CALCULO CONFORME INDICE PREFEITURA
A17: Área Parcelável | B17: =B16 -> 117208.4 | C17: =B17/B16 -> 1 | F17: Área Líquida | G17: CA | H17: Área Construtiva | I17: Apartamento Padrão | J17: Nº de Apartamentos | K17: Morador por Domicílio (IBGE) | L17: População Prevista | M17: Densidade Líquida
E18: Indice 4 | F18: 31336.65 | G18: 4 | H18: =G18*F18 -> 125346.6 | I18: 100 | J18: =H18/I18 -> 1253.466 | K18: 2.8 | L18: =K18*J18 -> 3509.7048 | M18: =L18/F18*10000 -> 1120
A19: Área a Parcelar | B19: =B17 -> 117208.4 | C19: 1 | E19: Indice 3 | F19: =B21-F18 -> 9147.93 | G19: 3 | H19: =G19*F19 -> 27443.79 | J19: =H19/I18 -> 274.4379 | L19: =K18*J19 -> 768.42612 | M19: =L19/F19*10000 -> 840
A20: Área Alienável | B20: =B21+B22+B23+B24 -> 64758.75 | C20: =B20/B19 -> 0.55250946 | E20: Total | F20: =F18+F19 -> 40484.58 | L20: =L18+L19 -> 4278.1309 | M20: =L20/F20*10000 -> 1056.731 | P20: =L20 -> 4278.1309
A21: Lotes Residenciais | B21: 40484.58 | C21: =B21/B19 -> 0.34540681
A22: Mall | B22: 8925.08 | C22: =B22/B19 -> 0.076147102
A23: Educação | B23: 5942.25 | C23: =B23/B19 -> 0.050698158 | F23: CALCULO COM DENSIDADE SUGERIDA
A24: Office | B24: 9406.84 | C24: =B24/B19 -> 0.080257388 | F24: Densidade Líquida | G24: Área Habitacional Total | I24: População Prevista | J24: Morador por Domicílio (IBGE) | K24: Nº de Apartamentos | L24: Apartamento Padrão | M24: Área Construtiva | N24: CA
A25: Área Verde / Praça | B25: 7929.92 | C25: =B25/B19 -> 0.067656584 | F25: 600 | G25: =B21/10000 -> 4.048458 | I25: =G25*F25 -> 2429.0748 | J25: 2.8 | K25: =I25/J25 -> 867.52671 | L25: 100 | M25: =K25*L25 -> 86752.671 | N25: =(M25/G25)/10000 -> 2.1428571
A26: Sistema Viário | B26: =B19-B20-B25 -> 44519.73 | C26: =B26/B19 -> 0.37983395
A29: ALDORA PARK
F30: CALCULO CONFORME INDICE PREFEITURA
A31: Área Total | B31: 307286.3 | C31: 1 | F31: Área Líquida | G31: CA | H31: Área Construtiva | I31: Apartamento Padrão | J31: Nº de Apartamentos | K31: Morador por Domicílio (IBGE) | L31: População Prevista | M31: Densidade Líquida
A32: Área Parcelável | B32: =B31 -> 307286.3 | C32: =B32/B31 -> 1 | E32: Indice 4 | F32: 49877.37 | G32: 4 | H32: =G32*F32 -> 199509.48 | I32: 100 | J32: =H32/I32 -> 1995.0948 | K32: 2.8 | L32: =K32*J32 -> 5586.2654 | M32: =L32/F32*10000 -> 1120
E33: Indice 3 | F33: 89793.52 | G33: 3 | H33: =G33*F33 -> 269380.56 | J33: =H33/I32 -> 2693.8056 | L33: =K32*J33 -> 7542.6557 | M33: =L33/F33*10000 -> 840
A34: Área a Parcelar | B34: =B32 -> 307286.3 | C34: 1 | E34: Total | F34: =F32+F33 -> 139670.89 | L34: =L32+L33 -> 13128.921 | M34: =L34/F34*10000 -> 939.98979 | P34: =L34 -> 13128.921
A35: Área Alienável | B35: =B36+B37 -> 150137.86 | C35: =B35/B34 -> 0.48859276
A36: Lotes Residenciais | B36: 139670.89 | C36: =B36/B34 -> 0.45453016
A37: Mall | B37: 10466.97 | C37: =B37/B34 -> 0.034062599 | F37: CALCULO COM DENSIDADE SUGERIDA
A38: Área Verde / Praça | B38: 67225.47 | C38: =B38/B34 -> 0.21877145 | F38: Densidade Líquida | G38: Área Habitacional Total | I38: População Prevista | J38: Morador por Domicílio (IBGE) | K38: Nº de Apartamentos | L38: Apartamento Padrão | M38: Área Construtiva | N38: CA
A39: Sistema Viário | B39: =B34-B35-B38 -> 89922.97 | C39: =B39/B34 -> 0.29263579 | F39: 600 | G39: =B36/10000 -> 13.967089 | I39: =G39*F39 -> 8380.2534 | J39: 2.8 | K39: =I39/J39 -> 2992.9476 | L39: 100 | M39: =K39*L39 -> 299294.76 | N39: =(M39/G39)/10000 -> 2.1428571
A42: ALDORA VITTA
A44: Área Total | B44: 285560.17 | C44: 1 | F44: CALCULO CONFORME INDICE PREFEITURA
A45: Área de Preversação Permanente | B45: 98424.41 | F45: Área Líquida | G45: CA | H45: Área Construtiva | I45: Apartamento Padrão | J45: Nº de Apartamentos | K45: Morador por Domicílio (IBGE) | L45: População Prevista | M45: Densidade Líquida
A46: Área Parcelável | B46: =B44-B45 -> 187135.76 | C46: =B46/B44 -> 0.65532865 | E46: Indice 4 | F46: 50947.26 | G46: 4 | H46: =G46*F46 -> 203789.04 | I46: 100 | J46: =H46/I46 -> 2037.8904 | K46: 2.8 | L46: =K46*J46 -> 5706.0931 | M46: =L46/F46*10000 -> 1120
E47: Indice 3 | F47: =B50-F46 -> 53456.07 | G47: 3 | H47: =G47*F47 -> 160368.21 | J47: =H47/I46 -> 1603.6821 | L47: =K46*J47 -> 4490.3099 | M47: =L47/F47*10000 -> 840
A48: Área a Parcelar | B48: =B46 -> 187135.76 | C48: 1 | E48: Total | F48: =F46+F47 -> 104403.33 | L48: =L46+L47 -> 10196.403 | M48: =L48/F48*10000 -> 976.6358 | P48: =L48 -> 10196.403
A49: Área Alienável | B49: =B50+B51 -> 112302.41 | C49: =B49/B48 -> 0.60011197
A50: Lotes Residenciais | B50: 104403.33 | C50: =B50/B48 -> 0.55790155
A51: Lotes Comerciais | B51: 7899.08 | C51: =B51/B48 -> 0.042210425 | F51: CALCULO COM DENSIDADE SUGERIDA
A52: Área Verde / Praça | B52: 25487.15 | C52: =B52/B48 -> 0.13619604 | F52: Densidade Líquida | G52: Área Habitacional Total | I52: População Prevista | J52: Morador por Domicílio (IBGE) | K52: Nº de Apartamentos | L52: Apartamento Padrão | M52: Área Construtiva | N52: CA
A53: Sistema Viário | B53: =B48-B49-B52 -> 49346.2 | C53: =B53/B48 -> 0.26369198 | F53: 600 | G53: =B50/10000 -> 10.440333 | I53: =G53*F53 -> 6264.1998 | J53: 2.8 | K53: =I53/J53 -> 2237.2142 | L53: 100 | M53: =K53*L53 -> 223721.42 | N53: =(M53/G53)/10000 -> 2.1428571
A56: ALDORA NEXUS
A58: Área Total | B58: 269343.71 | C58: 1
A59: Área de Preversação Permanente | B59: 99324.43 | C59: =B59/B58 -> 0.36876462
A60: Área Parcelável | B60: =B58-B59 -> 170019.28 | C60: =B60/B58 -> 0.63123538
F61: CALCULO CONFORME INDICE PREFEITURA
A62: Área a Parcelar | B62: =B60 -> 170019.28 | C62: 1 | F62: Área Líquida | G62: CA | H62: Área Construtiva | I62: Apartamento Padrão | J62: Nº de Apartamentos | K62: Morador por Domicílio (IBGE) | L62: População Prevista | M62: Densidade Líquida
A63: Área Alienável | B63: =B64+B66+B65 -> 102029.4 | C63: =B63/B62 -> 0.60010488 | E63: Indice 3 | F63: =B64/2 -> 38350.585 | G63: 3 | H63: =G63*F63 -> 115051.76 | I63: 100 | J63: =H63/I63 -> 1150.5176 | K63: 2.8 | L63: =K63*J63 -> 3221.4491 | M63: =L63/F63*10000 -> 840 | P63: =L63 -> 3221.4491
A64: Lotes Uso Misto | B64: 76701.17 | C64: =B64/B62 -> 0.45113219
A65: Lotes Start-up | B65: 15292.54 | C65: =B65/B62 -> 0.089945917
A66: Lotes Hub Negócios | B66: 10035.69 | C66: =B66/B62 -> 0.059026776
A67: Área Verde / Praça | B67: 35523.64 | C67: =B67/B62 -> 0.20893889
A68: Sistema Viário | B68: =B62-B63-B67 -> 32466.24 | C68: =B68/B62 -> 0.19095623
A71: LOTEAMENTO FECHADO JARDIM
A73: JARDIM CHAMBOARD
A75: Área Total | B75: 250376.16 | C75: 1
A76: Área Parcelável | B76: =B75 -> 250376.16 | C76: 1
A78: Área a Parcelar | B78: =B76 -> 250376.16 | C78: 1 | F78: Área Líquida | G78: Lotes | H78: Morador / Domicílio (IBGE) | I78: População Prevista | J78: Densidade Líquida
A79: Área Alienável | B79: =B80+B81+B82 -> 130760.8 | C79: =B79/B78 -> 0.52225739 | F79: =B80 -> 128267.42 | G79: 208 | H79: 2.8 | I79: =H79*G79 -> 582.4 | J79: =I79/F79*10000 -> 45.405139 | P79: =I79 -> 582.4
A80: Lotes Residenciais | B80: 128267.42 | C80: =B80/B78 -> 0.51229885
A81: Lotes Portaria | B81: 1235 | C81: =B81/B78 -> 0.0049325782
A82: Lotes Equipamentos Lazer | B82: 1258.38 | C82: =B82/B78 -> 0.0050259577
A83: Área Verde | B83: 31796.02 | C83: =B83/B78 -> 0.126993
A84: Sistema Viário | B84: =B78-B79-B83 -> 87819.34 | C84: =B84/B78 -> 0.35074961
A87: CONDOMINIO 02
A89: Área Total | B89: 192470.17 | C89: 1
A90: Área Parcelável | B90: =B89 -> 192470.17 | C90: 1
A92: Área a Parcelar | B92: =B90 -> 192470.17 | C92: 1 | F92: Área Líquida | G92: Lotes | H92: Morador / Domicílio (IBGE) | I92: População Prevista | J92: Densidade Líquida
A93: Área Alienável | B93: =B94+B95 -> 76835.08 | C93: =B93/B92 -> 0.39920513 | F93: =B94 -> 75635.08 | G93: 131 | H93: 2.8 | I93: =H93*G93 -> 366.8 | J93: =I93/F93*10000 -> 48.496015 | P93: =I93 -> 366.8
A94: Lotes Residenciais | B94: 75635.08 | C94: =B94/B92 -> 0.3929704
A95: Lotes Portaria | B95: 1200 | C95: =B95/B92 -> 0.0062347324
A96: Área Verde | B96: 36913.45 | C96: =B96/B92 -> 0.1917879 | M96: POPULAÇÃO TOTAL ESTIMADA | P96: =P93+P79+P63+P48+P34+P20+P5 -> 35964.294
A97: Sistema Viário | B97: =B92-B93-B96 -> 78721.64 | C97: =B97/B92 -> 0.40900696
B101: =SUM(B89,B75,B58,B44,B31,B16,B3) -> 1481988.6
B102: =B101/(100*100) -> 148.19886
B103: =P96/B102 -> 242.67591 | C103: hab. / ha
A106: EMPREENDIMENTOS | B106: TORRES | C106: APTO / LOTE | D106: COEF. | E106: POPULAÇÃO
E107: Est. CDJ | F107: Est. G4
A108: =Empreendimentos!A8 -> AL'DORA TOWN - VERSAILLES | B108: =Empreendimentos!L8 -> 14 | C108: 150 | D108: 2.8 | E108: =B108*C108*D108 -> 5880 | F108: =P5 -> 4190.1899
A109: =Empreendimentos!A41 -> JARDIM CHAMBORD | C109: =Empreendimentos!J42 -> 208 | D109: 2.8 | E109: =C109*D109 -> 582.4 | F109: =P79 -> 582.4
A110: =Empreendimentos!A57 -> AL'DORA TOWN | B110: =Empreendimentos!L58+Empreendimentos!L67+Empreendimentos!L69 -> 13 | C110: 150 | D110: 2.8 | E110: =B110*C110*D110 -> 5460 | F110: =P20 -> 4278.1309
A111: =Empreendimentos!A72 -> JARDIM 03 | C111: =Empreendimentos!J73 -> 180 | D111: 2.8 | E111: =C111*D111 -> 504 | F111: =P93 -> 366.8
A112: =Empreendimentos!A76 -> AL'DORA PARK | B112: =Empreendimentos!L76-Empreendimentos!L83 -> 47 | C112: 150 | D112: 2.8 | E112: =B112*C112*D112 -> 19740 | F112: =P34 -> 13128.921
A113: =Empreendimentos!A104 -> AL'DORA VITTA | B113: =Empreendimentos!L104-Empreendimentos!L105 -> 30 | C113: 150 | D113: 2.8 | E113: =B113*C113*D113 -> 12600 | F113: =P48 -> 10196.403
A114: =Empreendimentos!A124 -> AL'DORA NEXUS GENOVA | B114: =Empreendimentos!L126 -> 5 | C114: =150/24*4 -> 25 | D114: 2.8 | E114: =B114*C114*D114 -> 350
A115: =Empreendimentos!A130 -> AL'DORA NEXUS | B115: =Empreendimentos!L130 -> 24 | C115: =(15*150+9*60)/24 -> 116.25 | D115: 2.8 | E115: =B115*C115*D115 -> 7812 | F115: =P63 -> 3221.4491
A116: =Empreendimentos!A152 -> JARDIM 04 | C116: =Empreendimentos!J153 -> 260 | D116: 2.8 | E116: =C116*D116 -> 728
A117: =Empreendimentos!A156 -> JARDIM 05 | C117: =Empreendimentos!J157 -> 290 | D117: 2.8 | E117: =C117*D117 -> 812
E118: =SUM(E108:E117) -> 54468.4 | F118: =SUM(F108:F117) -> 35964.294
D119: AREA TOTAL HECTARE | E119: =(B101+Empreendimentos!D153+Empreendimentos!D157)/(100*100) -> 195.21185 | F119: =B102 -> 148.19886
D120: HABITANTES / HECTARE | E120: =E118/E119 -> 279.022 | F120: =F118/F119 -> 242.67591
A123: AREA PARQUE | B123: NUCLEOS VERDES | C123: PARQUE LINEARES | D123: APP
A125: =A108 -> AL'DORA TOWN - VERSAILLES | B125: =Empreendimentos!D36 -> 17160
A126: =A109 -> JARDIM CHAMBORD
A127: =A110 -> AL'DORA TOWN | B127: =(Empreendimentos!D58+Empreendimentos!D60+Empreendimentos!D62+Empreendimentos!D67+Empreendimentos!D69)*9% -> 5828.6895
A128: =A111 -> JARDIM 03
A129: =A112 -> AL'DORA PARK | B129: =Empreendimentos!D101 -> 30160.271
...

Sheet POPULAÇÃO ATENDIDA
A1: DADOS DEMOGRÁFICOS
A2: DISTRIBUIÇÃO E EVOLUÇÃO POPULACIONAL
A3: A população residente total na Área de Influência em 2017 é estimada em 103,7 mil habitantes, dos quais 89% estão na Área Secundária.
A4: População estimada 2025, 761.835 pessoas [2025]
C6: 2017 | E6: 2025
A7: Área de Influência | B7: TGCA* | C7: População | D7: Part. | E7: População | F7: Part.
A8: Primaria | B8: 0.079 | C8: 11816 | D8: =C8/C10 -> 0.11392869 | E8: =C8/$C$12*$E$12 -> 12943.873 | F8: =E8/E10 -> 0.11392869
A9: Secundaria | B9: 0.024 | C9: 91898 | D9: =C9/C10 -> 0.88607131 | E9: =C9/$C$12*$E$12 -> 100669.94 | F9: =E9/E10 -> 0.88607131
C10: =SUM(C8:C9) -> 103714 | D10: =SUM(D8:D9) -> 1 | E10: =SUM(E8:E9) -> 113613.82 | F10: =SUM(F8:F9) -> 1
A12: POPULAÇÃO | C12: 695452 | E12: 761835

Sheet Cronogramaa Fisico
A2: CRONOGRAMA FÍSICO-FINANCEIRO
A3: CLIENTE: | B3: CIDADE JARDIM EMPREENDIMENTOS
A4: OBRA: | B4: AL' DORA CIDADE JARDIM
A5: DATA | B5: 45968
A6: REVISÃO: | B6: 01
A8: DISCRIMINAÇÃO | C8: AREA | D8: 1° ano | E8: 2° ano | F8: 3° ano | G8: 4° ano | H8: 5° ano | I8: 6° ano | J8: 7° ano | K8: 8° ano | L8: 9° ano | M8: 10° ano | N8: 11° ano | O8: 12° ano | P8: 13° ano | Q8: 14° ano | R8: 15° ano | S8: 16° ano | T8: 17° ano | U8: 18° ano | V8: 19° ano | W8: 20° ano | X8: 21° ano | Y8: 22° ano | Z8: 23° ano | AA8: 24° ano | AB8: 25° ano | AC8: 26° | AD8: 27 | AE8: 28 | AF8: 29 | AG8: 30 | AH8: 31 | AI8: 32 | AJ8: 33 | AK8: 34 | AL8: 35 | AM8: 36 | AN8: 37 | AO8: 38 | AP8: 39 | AQ8: 40 | AR8: 41 | AS8: 42 | AT8: 43 | AU8: 44 | AV8: 45 | AW8: 46 | AX8: 47 | AY8: 48 | AZ8: 49 | BA8: 50° ano
D9: 2026 | E9: 2027 | F9: 2028 | G9: 2029 | H9: 2030 | I9: 2031 | J9: 2032 | K9: 2033 | L9: 2034 | M9: 2035 | N9: 2036 | O9: 2037 | P9: 2038 | Q9: 2039 | R9: 2040 | S9: 2041 | T9: 2042 | U9: 2043 | V9: 2044 | W9: 2045 | X9: 2046 | Y9: 2047 | Z9: 2048 | AA9: 2049 | AB9: 2050 | AC9: 2051 | AD9: 2052 | AE9: 2053 | AF9: 2054 | AG9: 2055 | AH9: 2056 | AI9: 2057 | AJ9: 2058 | AK9: 2059 | AL9: 2060 | AM9: 2061 | AN9: 2062 | AO9: 2063 | AP9: 2064 | AQ9: 2065 | AR9: 2066 | AS9: 2067 | AT9: 2068 | AU9: 2069 | AV9: 2070 | AW9: 2071 | AX9: 2072 | AY9: 2073 | AZ9: 2074 | BA9: 2076
B11: INFRA ESTRUTURA
A12: 1.0 | B12: FASE 01 - AL'DORA VERSAILLES | BB12: =SUM(D12:BA12) -> 0
A13: 1.1 | B13: Al'dora Town - Versailles | D13: 0.025688309 | E13: 0.045 | F13: 0.06 | G13: 0.08 | H13: 0.08 | I13: 0.09 | J13: 0.1 | K13: 0.11 | L13: 0.1 | M13: 0.09 | N13: 0.07 | O13: 0.07 | P13: 0.05 | Q13: 0.02 | R13: 0.009941956 | BB13: =SUM(D13:BA13) -> 1.0006303
BB14: =SUM(D14:BA14) -> 0
A15: 2.0 | B15: FASE 02 - JARDIM CHAMBORD / AL'DORA TOWN | BB15: =SUM(D15:BA15) -> 0
A16: 2.1 | B16: Jardim Chambord | D16: 0.2 | E16: 0.5 | F16: 0.3 | BB16: =SUM(D16:BA16) -> 1
A17: 2.2 | B17: Al'dora Town - Infra estrutura | E17: 0.4 | F17: 0.6 | BB17: =SUM(D17:BA17) -> 1
A18: 2.3 | B18: Mall | F18: 0.2 | G18: 0.4 | L18: 0.2 | M18: 0.2 | BB18: =SUM(D18:BA18) -> 1
A19: 2.4 | B19: Escolas | F19: 0.2 | G19: 0.3 | L19: 0.1 | M19: 0.4 | BB19: =SUM(D19:BA19) -> 1
A20: 2.5 | B20: Edificações | F20: 0.02 | G20: 0.03 | H20: 0.04 | I20: 0.06 | J20: 0.07 | K20: 0.08 | L20: 0.1 | M20: 0.1 | N20: 0.11 | O20: 0.1 | P20: 0.1 | Q20: 0.08 | R20: 0.06 | S20: 0.04 | T20: 0.01 | BB20: =SUM(D20:BA20) -> 1
BB21: =SUM(D21:BA21) -> 0
A22: 3.0 | B22: FASE 03 - JARDIM 03 | BB22: =SUM(D22:BA22) -> 0
A23: 3.1 | B23: Jardim Condomínio Fechado | F23: 0.3 | G23: 0.4 | H23: 0.3 | BB23: =SUM(D23:BA23) -> 1
BB24: =SUM(D24:BA24) -> 0
A25: 4.0 | B25: FASE 04 - INFRA ESTRUTURA - | BB25: =SUM(D25:BA25) -> 0
A26: 4.1 | B26: Gleba H - Etapa 01 | BB26: =SUM(D26:BA26) -> 0
B27: EEE e Coletor Tronco | F27: 0.4 | G27: 0.6 | BB27: =SUM(D27:BA27) -> 1
B28: Adutora | G28: 0.4 | H28: 0.6 | BB28: =SUM(D28:BA28) -> 1
A29: 4.2 | B29: Gleba 6 e 7 - Etapa 02 | BB29: =SUM(D29:BA29) -> 0
B30: EEE e Coletor Tronco | K30: 0.3 | L30: 0.7 | BB30: =SUM(D30:BA30) -> 1
B31: Adutora | K31: 0.3 | L31: 0.7 | BB31: =SUM(D31:BA31) -> 1
BB32: =SUM(D32:BA32) -> 0
A33: 5.0 | B33: FASE 05 - AL'DORA NEXUS GENOVA | BB33: =SUM(D33:BA33) -> 0
A34: 5.1 | B34: Polo Corporativo - Etapa 01, 02 e 03 | E34: 0.1 | F34: 0.125 | G34: 0.15 | H34: 0.1 | I34: 0.05 | J34: 0.05 | M34: 0.06 | N34: 0.14 | Q34: 0.085 | R34: 0.14 | BB34: =SUM(D34:BA34) -> 1
BB35: =SUM(D35:BA35) -> 0
A36: 6.0 | B36: FASE 06 - AL'DORA PARK | BB36: =SUM(D36:BA36) -> 0
A37: 6.1 | B37: Infra estrutura - Etapa 01, 02 e 03 | H37: 0.05 | I37: 0.2 | J37: 0.15 | O37: 0.2 | P37: 0.15 | S37: 0.15 | T37: 0.1 | BB37: =SUM(D37:BA37) -> 1
A38: 6.2 | B38: Edificações | J38: 0.01 | K38: 0.01 | L38: 0.01 | M38: 0.013 | N38: 0.02 | O38: 0.022 | P38: 0.025 | Q38: 0.03 | R38: 0.03 | S38: 0.03 | T38: 0.03 | U38: 0.03 | V38: 0.03 | W38: 0.03 | X38: 0.03 | Y38: 0.03 | Z38: 0.03 | AA38: 0.03 | AB38: 0.03 | AC38: 0.03 | AD38: 0.03 | AE38: 0.03 | AF38: 0.03 | AG38: 0.02 | AH38: 0.02 | AI38: 0.02 | AJ38: 0.02 | AK38: 0.02 | AL38: 0.02 | AM38: 0.02 | AN38: 0.02 | AO38: 0.02 | AP38: 0.02 | AQ38: 0.02 | AR38: 0.02 | AS38: 0.02 | AT38: 0.02 | AU38: 0.02 | AV38: 0.02 | AW38: 0.02 | AX38: 0.02 | AY38: 0.02 | AZ38: 0.02 | BA38: 0.01 | BB38: =SUM(D38:BA38) -> 1
BB39: =SUM(D39:BA39) -> 0
A40: 7.0 | B40: FASE 07 - JARDIM 04 | BB40: =SUM(D40:BA40) -> 0
A41: 71 | B41: Jardim Condomínio Fechado | K41: 0.4 | L41: 0.6 | BB41: =SUM(D41:BA41) -> 1
BB42: =SUM(D42:BA42) -> 0
A43: 8.0 | B43: FASE 08 - AL'DORA NEXUS | BB43: =SUM(D43:BA43) -> 0
A44: 8.1 | B44: Infra estrutura - Etapa 01 e 02 | M44: 0.2 | N44: 0.3 | U44: 0.2 | V44: 0.3 | BB44: =SUM(D44:BA44) -> 1
A45: 8.2 | B45: Edificações | O45: 0.02 | P45: 0.03 | Q45: 0.03 | R45: 0.03 | S45: 0.03 | T45: 0.04 | U45: 0.04 | V45: 0.04 | W45: 0.04 | X45: 0.04 | Y45: 0.04 | Z45: 0.04 | AA45: 0.05 | AB45: 0.05 | AC45: 0.03 | AD45: 0.02 | AE45: 0.02 | AF45: 0.02 | AG45: 0.22 | AH45: 0.02 | AI45: 0.02 | AJ45: 0.02 | AK45: 0.02 | AL45: 0.02 | AM45: 0.01 | AN45: 0.01 | AO45: 0.01 | AP45: 0.01 | AQ45: 0.01 | AR45: 0.01 | AS45: 0.01 | BB45: =SUM(D45:BA45) -> 1
BB46: =SUM(D46:BA46) -> 0
A47: 9.0 | B47: FASE 09 - AL'DORA VITA | BB47: =SUM(D47:BA47) -> 0
A48: 9.1 | B48: Infra estrutura - Etapa 01 e 02 | Q48: 0.2 | R48: 0.3 | W48: 0.2 | X48: 0.3 | BB48: =SUM(D48:BA48) -> 1
A49: 9.2 | B49: Edificações | S49: 0.02 | T49: 0.02 | U49: 0.03 | V49: 0.03 | W49: 0.03 | X49: 0.03 | Y49: 0.04 | Z49: 0.04 | AA49: 0.04 | AB49: 0.04 | AC49: 0.05 | AD49: 0.05 | AE49: 0.05 | AF49: 0.04 | AG49: 0.04 | AH49: 0.04 | AI49: 0.04 | AJ49: 0.04 | AK49: 0.04 | AL49: 0.03 | AM49: 0.03 | AN49: 0.025 | AO49: 0.025 | AP49: 0.025 | AQ49: 0.025 | AR49: 0.02 | AS49: 0.02 | AT49: 0.02 | AU49: 0.01 | AV49: 0.01 | AW49: 0.01 | AX49: 0.01 | AY49: 0.01 | AZ49: 0.01 | BA49: 0.01 | BB49: =SUM(D49:BA49) -> 1
BB50: =SUM(D50:BA50) -> 0
A51: 10.0 | B51: FASE 010 - JARDIM 05 | BB51: =SUM(D51:BA51) -> 0
A52: 10.1 | B52: Jardim Condomínio Fechado | Q52: 0.4 | R52: 0.6 | BB52: =SUM(D52:BA52) -> 1
BB53: =SUM(D53:BA53) -> 0
BB54: =SUM(D54:BA54) -> 0
BB55: =SUM(D55:BA55) -> 0

Sheet Referencias
A3: Empreendimento Incorporadora | B3: Área privativa(AP) (m²) | C3: Área total geral(AT) (m²) | D3: Área do terreno (m²) | E3: N° unidades
A4: Domum Bild | B4: 15366.36 | C4: 26875.46 | D4: 4793.31 | E4: 126 | F4: =B4/D4 -> 3.2057931
A5: GrandVerse Place Perplan | B5: 16991.98 | C5: 26758.88 | D5: 4439.5 | E5: 156 | F5: =B5/D5 -> 3.8274535
A6: Casa'Alta Perplan | B6: 13386.08 | C6: 22689.57 | D6: 4000 | F6: =B6/D6 -> 3.34652
A7: Nuage Perplan | B7: 11659.35 | C7: 19618.39 | D7: 3100 | F7: =B7/D7 -> 3.7610806
A8: Solei Inconew | B8: 15244.59 | C8: 26347.06 | D8: 4168.53 | E8: 182 | F8: =B8/D8 -> 3.6570662
A9: Tramonto Maxi | B9: 9422.8 | C9: 15395.59 | D9: 2355.5 | F9: =B9/D9 -> 4.0003396
A10: Grecco Maxi | B10: 11301 | C10: 18576.26 | D10: 3767 | E10: 125 | F10: =B10/D10 -> 3
A11: Liwo Working e Living Maxi | B11: 12558.41 | C11: 24288.11 | D11: 3200.58 | E11: 111 | F11: =B11/D11 -> 3.9237919
B12: =AVERAGE(B4:B5,B8,B10:B11) -> 14292.468 | C12: =AVERAGE(C4:C5,C8,C10:C11) -> 24569.154 | D12: =AVERAGE(D4:D11) -> 3728.0525 | E12: =AVERAGE(E4:E11) -> 140 | F12: =AVERAGE(F4:F11) -> 3.5902556 | G12: =C12/E12 -> 175.49396
B14: =B12/E12 -> 102.08906
